{
	"<a id=\"ASASSN-16fm\">ASASSN-16fm</a>":{
		"schema":"https://github.com/astrocatalogs/supernovae/blob/d3ef5fc/SCHEMA.md",
		"name":"<a id=\"ASASSN-16fm\">ASASSN-16fm</a>",
		"sources":[
			{
				"name":"ATel 9080",
				"bibcode":"2016ATel.9080....1V",
				"reference":"Villanueva et al. (2016)",
				"url":"http://www.astronomerstelegram.org/?read=9080",
				"alias":"1"
			},
			{
				"name":"Latest Supernovae",
				"secondary":true,
				"url":"http://www.rochesterastronomy.org/snimages/snredshiftall.html",
				"alias":"2"
			},
			{
				"name":"The Open Supernova Catalog",
				"bibcode":"2017ApJ...835...64G",
				"reference":"Guillochon et al. (2017)",
				"secondary":true,
				"url":"https://sne.space",
				"alias":"3"
			}
		],
		"alias":[
			{
				"value":"<a id=\"ASASSN-16fm\">ASASSN-16fm</a>",
				"source":"1,2"
			},
			{
				"value":"AT2016cny",
				"source":"1,2"
			},
			{
				"value":"ASASSN-16fm",
				"source":"1,2"
			}
		],
		"claimedtype":[
			{
				"value":"CV",
				"source":"1,2"
			}
		],
		"dec":[
			{
				"value":"+22:42:09.66",
				"u_value":"degrees",
				"source":"1,2"
			}
		],
		"discoverdate":[
			{
				"value":"2016/05/13",
				"source":"1,2"
			}
		],
		"discoverer":[
			{
				"value":"ASAS-SN",
				"source":"1,2"
			}
		],
		"maxappmag":[
			{
				"value":"16.9",
				"derived":true,
				"source":"1,2,3"
			}
		],
		"maxdate":[
			{
				"value":"2016/05/13",
				"derived":true,
				"source":"1,2,3"
			}
		],
		"maxvisualappmag":[
			{
				"value":"16.9",
				"derived":true,
				"source":"1,2,3"
			}
		],
		"maxvisualdate":[
			{
				"value":"2016/05/13",
				"derived":true,
				"source":"1,2,3"
			}
		],
		"ra":[
			{
				"value":"20:22:50.125",
				"u_value":"hours",
				"source":"1,2"
			}
		],
		"photometry":[
			{
				"time":"57520.5",
				"magnitude":"16.9",
				"u_time":"MJD",
				"source":"1,2"
			},
			{
				"time":"57521.0",
				"magnitude":"16.9",
				"u_time":"MJD",
				"source":"1,2"
			}
		]
	}
}