{
	"AT2021vtr":{
		"schema":"https://github.com/astrocatalogs/supernovae/blob/d3ef5fc/SCHEMA.md",
		"name":"AT2021vtr",
		"sources":[
			{
				"name":"Transient Name Server",
				"url":"https://www.wis-tns.org/object/2021vtr",
				"alias":"1"
			},
			{
				"name":"Gaia Photometric Science Alerts",
				"url":"http://gsaweb.ast.cam.ac.uk/alerts/alertsindex",
				"alias":"2"
			},
			{
				"name":"Latest Supernovae",
				"secondary":true,
				"url":"http://www.rochesterastronomy.org/snimages/snredshiftall.html",
				"alias":"3"
			},
			{
				"name":"The Open Supernova Catalog",
				"bibcode":"2017ApJ...835...64G",
				"reference":"Guillochon et al. (2017)",
				"secondary":true,
				"url":"https://sne.space",
				"alias":"4"
			}
		],
		"alias":[
			{
				"value":"AT2021vtr",
				"source":"1,2,3"
			},
			{
				"value":"ZTF20acbelwt",
				"source":"1,3"
			},
			{
				"value":"Gaia22arb",
				"source":"1,3"
			}
		],
		"claimedtype":[
			{
				"value":"AGN",
				"source":"1,3"
			}
		],
		"dec":[
			{
				"value":"+20:23:44.38",
				"u_value":"degrees",
				"source":"1,3"
			},
			{
				"value":"+20:23:44.52",
				"u_value":"degrees",
				"source":"2"
			}
		],
		"discoverdate":[
			{
				"value":"2021/07/17",
				"source":"1,3"
			}
		],
		"discoverer":[
			{
				"value":"ZTF",
				"source":"1,3"
			}
		],
		"maxappmag":[
			{
				"value":"17.33",
				"derived":true,
				"source":"2,4"
			}
		],
		"maxband":[
			{
				"value":"G",
				"derived":true,
				"source":"2,4"
			}
		],
		"maxdate":[
			{
				"value":"2022/02/17",
				"derived":true,
				"source":"2,4"
			}
		],
		"maxvisualappmag":[
			{
				"value":"17.33",
				"derived":true,
				"source":"2,4"
			}
		],
		"maxvisualband":[
			{
				"value":"G",
				"derived":true,
				"source":"2,4"
			}
		],
		"maxvisualdate":[
			{
				"value":"2022/02/17",
				"derived":true,
				"source":"2,4"
			}
		],
		"ra":[
			{
				"value":"01:52:30.257",
				"u_value":"hours",
				"source":"1,3"
			},
			{
				"value":"01:52:30.264",
				"u_value":"hours",
				"source":"2"
			}
		],
		"photometry":[
			{
				"time":"57204.56000",
				"band":"G",
				"e_magnitude":"0.0",
				"instrument":"Astrometric",
				"magnitude":"17.45",
				"telescope":"GAIA",
				"u_time":"MJD",
				"source":"2"
			},
			{
				"time":"57257.62700",
				"band":"G",
				"e_magnitude":"0.0",
				"instrument":"Astrometric",
				"magnitude":"17.36",
				"telescope":"GAIA",
				"u_time":"MJD",
				"source":"2"
			},
			{
				"time":"57395.09854",
				"band":"G",
				"e_magnitude":"0.0",
				"instrument":"Astrometric",
				"magnitude":"17.47",
				"telescope":"GAIA",
				"u_time":"MJD",
				"source":"2"
			},
			{
				"time":"57395.17253",
				"band":"G",
				"e_magnitude":"0.0",
				"instrument":"Astrometric",
				"magnitude":"17.45",
				"telescope":"GAIA",
				"u_time":"MJD",
				"source":"2"
			},
			{
				"time":"57423.58213",
				"band":"G",
				"e_magnitude":"0.0",
				"instrument":"Astrometric",
				"magnitude":"17.46",
				"telescope":"GAIA",
				"u_time":"MJD",
				"source":"2"
			},
			{
				"time":"57423.65612",
				"band":"G",
				"e_magnitude":"0.0",
				"instrument":"Astrometric",
				"magnitude":"17.45",
				"telescope":"GAIA",
				"u_time":"MJD",
				"source":"2"
			},
			{
				"time":"57444.83000",
				"band":"G",
				"e_magnitude":"0.0",
				"instrument":"Astrometric",
				"magnitude":"17.48",
				"telescope":"GAIA",
				"u_time":"MJD",
				"source":"2"
			},
			{
				"time":"57444.90399",
				"band":"G",
				"e_magnitude":"0.0",
				"instrument":"Astrometric",
				"magnitude":"17.49",
				"telescope":"GAIA",
				"u_time":"MJD",
				"source":"2"
			},
			{
				"time":"58099.09998",
				"band":"G",
				"e_magnitude":"0.0",
				"instrument":"Astrometric",
				"magnitude":"17.65",
				"telescope":"GAIA",
				"u_time":"MJD",
				"source":"2"
			},
			{
				"time":"58110.52994",
				"band":"G",
				"e_magnitude":"0.0",
				"instrument":"Astrometric",
				"magnitude":"17.64",
				"telescope":"GAIA",
				"u_time":"MJD",
				"source":"2"
			},
			{
				"time":"58110.60395",
				"band":"G",
				"e_magnitude":"0.0",
				"instrument":"Astrometric",
				"magnitude":"17.63",
				"telescope":"GAIA",
				"u_time":"MJD",
				"source":"2"
			},
			{
				"time":"58145.75023",
				"band":"G",
				"e_magnitude":"0.0",
				"instrument":"Astrometric",
				"magnitude":"17.68",
				"telescope":"GAIA",
				"u_time":"MJD",
				"source":"2"
			},
			{
				"time":"58145.82422",
				"band":"G",
				"e_magnitude":"0.0",
				"instrument":"Astrometric",
				"magnitude":"17.68",
				"telescope":"GAIA",
				"u_time":"MJD",
				"source":"2"
			},
			{
				"time":"58281.27595",
				"band":"G",
				"e_magnitude":"0.0",
				"instrument":"Astrometric",
				"magnitude":"17.65",
				"telescope":"GAIA",
				"u_time":"MJD",
				"source":"2"
			},
			{
				"time":"58281.34997",
				"band":"G",
				"e_magnitude":"0.0",
				"instrument":"Astrometric",
				"magnitude":"17.69",
				"telescope":"GAIA",
				"u_time":"MJD",
				"source":"2"
			},
			{
				"time":"58281.52613",
				"band":"G",
				"e_magnitude":"0.0",
				"instrument":"Astrometric",
				"magnitude":"17.69",
				"telescope":"GAIA",
				"u_time":"MJD",
				"source":"2"
			},
			{
				"time":"58297.03281",
				"band":"G",
				"e_magnitude":"0.0",
				"instrument":"Astrometric",
				"magnitude":"17.67",
				"telescope":"GAIA",
				"u_time":"MJD",
				"source":"2"
			},
			{
				"time":"58297.10683",
				"band":"G",
				"e_magnitude":"0.0",
				"instrument":"Astrometric",
				"magnitude":"17.69",
				"telescope":"GAIA",
				"u_time":"MJD",
				"source":"2"
			},
			{
				"time":"58332.51670",
				"band":"G",
				"e_magnitude":"0.0",
				"instrument":"Astrometric",
				"magnitude":"17.66",
				"telescope":"GAIA",
				"u_time":"MJD",
				"source":"2"
			},
			{
				"time":"58332.59072",
				"band":"G",
				"e_magnitude":"0.0",
				"instrument":"Astrometric",
				"magnitude":"17.66",
				"telescope":"GAIA",
				"u_time":"MJD",
				"source":"2"
			},
			{
				"time":"58472.06867",
				"band":"G",
				"e_magnitude":"0.0",
				"instrument":"Astrometric",
				"magnitude":"17.71",
				"telescope":"GAIA",
				"u_time":"MJD",
				"source":"2"
			},
			{
				"time":"58472.14266",
				"band":"G",
				"e_magnitude":"0.0",
				"instrument":"Astrometric",
				"magnitude":"17.69",
				"telescope":"GAIA",
				"u_time":"MJD",
				"source":"2"
			},
			{
				"time":"58490.81836",
				"band":"G",
				"e_magnitude":"0.0",
				"instrument":"Astrometric",
				"magnitude":"17.69",
				"telescope":"GAIA",
				"u_time":"MJD",
				"source":"2"
			},
			{
				"time":"58521.29775",
				"band":"G",
				"e_magnitude":"0.0",
				"instrument":"Astrometric",
				"magnitude":"17.71",
				"telescope":"GAIA",
				"u_time":"MJD",
				"source":"2"
			},
			{
				"time":"58655.39670",
				"band":"G",
				"e_magnitude":"0.0",
				"instrument":"Astrometric",
				"magnitude":"17.67",
				"telescope":"GAIA",
				"u_time":"MJD",
				"source":"2"
			},
			{
				"time":"58655.57288",
				"band":"G",
				"e_magnitude":"0.0",
				"instrument":"Astrometric",
				"magnitude":"17.70",
				"telescope":"GAIA",
				"u_time":"MJD",
				"source":"2"
			},
			{
				"time":"58678.32524",
				"band":"G",
				"e_magnitude":"0.0",
				"instrument":"Astrometric",
				"magnitude":"17.63",
				"telescope":"GAIA",
				"u_time":"MJD",
				"source":"2"
			},
			{
				"time":"58678.39926",
				"band":"G",
				"e_magnitude":"0.0",
				"instrument":"Astrometric",
				"magnitude":"17.66",
				"telescope":"GAIA",
				"u_time":"MJD",
				"source":"2"
			},
			{
				"time":"58706.75844",
				"band":"G",
				"e_magnitude":"0.0",
				"instrument":"Astrometric",
				"magnitude":"17.65",
				"telescope":"GAIA",
				"u_time":"MJD",
				"source":"2"
			},
			{
				"time":"58706.93462",
				"band":"G",
				"e_magnitude":"0.0",
				"instrument":"Astrometric",
				"magnitude":"17.64",
				"telescope":"GAIA",
				"u_time":"MJD",
				"source":"2"
			},
			{
				"time":"58839.58501",
				"band":"G",
				"e_magnitude":"0.0",
				"instrument":"Astrometric",
				"magnitude":"17.60",
				"telescope":"GAIA",
				"u_time":"MJD",
				"source":"2"
			},
			{
				"time":"58839.65902",
				"band":"G",
				"e_magnitude":"0.0",
				"instrument":"Astrometric",
				"magnitude":"17.55",
				"telescope":"GAIA",
				"u_time":"MJD",
				"source":"2"
			},
			{
				"time":"58861.36273",
				"band":"G",
				"e_magnitude":"0.0",
				"instrument":"Astrometric",
				"magnitude":"17.59",
				"telescope":"GAIA",
				"u_time":"MJD",
				"source":"2"
			},
			{
				"time":"58861.43672",
				"band":"G",
				"e_magnitude":"0.0",
				"instrument":"Astrometric",
				"magnitude":"17.61",
				"telescope":"GAIA",
				"u_time":"MJD",
				"source":"2"
			},
			{
				"time":"58889.48345",
				"band":"G",
				"e_magnitude":"0.0",
				"instrument":"Astrometric",
				"magnitude":"17.57",
				"telescope":"GAIA",
				"u_time":"MJD",
				"source":"2"
			},
			{
				"time":"59029.29479",
				"band":"G",
				"e_magnitude":"0.0",
				"instrument":"Astrometric",
				"magnitude":"17.63",
				"telescope":"GAIA",
				"u_time":"MJD",
				"source":"2"
			},
			{
				"time":"59029.36880",
				"band":"G",
				"e_magnitude":"0.0",
				"instrument":"Astrometric",
				"magnitude":"17.66",
				"telescope":"GAIA",
				"u_time":"MJD",
				"source":"2"
			},
			{
				"time":"59055.16023",
				"band":"G",
				"e_magnitude":"0.0",
				"instrument":"Astrometric",
				"magnitude":"17.57",
				"telescope":"GAIA",
				"u_time":"MJD",
				"source":"2"
			},
			{
				"time":"59064.01601",
				"band":"G",
				"e_magnitude":"0.0",
				"instrument":"Astrometric",
				"magnitude":"17.59",
				"telescope":"GAIA",
				"u_time":"MJD",
				"source":"2"
			},
			{
				"time":"59064.09001",
				"band":"G",
				"e_magnitude":"0.0",
				"instrument":"Astrometric",
				"magnitude":"17.55",
				"telescope":"GAIA",
				"u_time":"MJD",
				"source":"2"
			},
			{
				"time":"59203.31742",
				"band":"G",
				"e_magnitude":"0.0",
				"instrument":"Astrometric",
				"magnitude":"17.41",
				"telescope":"GAIA",
				"u_time":"MJD",
				"source":"2"
			},
			{
				"time":"59203.39142",
				"band":"G",
				"e_magnitude":"0.0",
				"instrument":"Astrometric",
				"magnitude":"17.41",
				"telescope":"GAIA",
				"u_time":"MJD",
				"source":"2"
			},
			{
				"time":"59222.56649",
				"band":"G",
				"e_magnitude":"0.0",
				"instrument":"Astrometric",
				"magnitude":"17.40",
				"telescope":"GAIA",
				"u_time":"MJD",
				"source":"2"
			},
			{
				"time":"59222.64049",
				"band":"G",
				"e_magnitude":"0.0",
				"instrument":"Astrometric",
				"magnitude":"17.39",
				"telescope":"GAIA",
				"u_time":"MJD",
				"source":"2"
			},
			{
				"time":"59252.62072",
				"band":"G",
				"e_magnitude":"0.0",
				"instrument":"Astrometric",
				"magnitude":"17.46",
				"telescope":"GAIA",
				"u_time":"MJD",
				"source":"2"
			},
			{
				"time":"59386.82191",
				"band":"G",
				"e_magnitude":"0.0",
				"instrument":"Astrometric",
				"magnitude":"17.42",
				"telescope":"GAIA",
				"u_time":"MJD",
				"source":"2"
			},
			{
				"time":"59386.89591",
				"band":"G",
				"e_magnitude":"0.0",
				"instrument":"Astrometric",
				"magnitude":"17.43",
				"telescope":"GAIA",
				"u_time":"MJD",
				"source":"2"
			},
			{
				"time":"59410.32384",
				"band":"G",
				"e_magnitude":"0.0",
				"instrument":"Astrometric",
				"magnitude":"17.41",
				"telescope":"GAIA",
				"u_time":"MJD",
				"source":"2"
			},
			{
				"time":"59439.88932",
				"band":"G",
				"e_magnitude":"0.0",
				"instrument":"Astrometric",
				"magnitude":"17.34",
				"telescope":"GAIA",
				"u_time":"MJD",
				"source":"2"
			},
			{
				"time":"59577.86273",
				"band":"G",
				"e_magnitude":"0.0",
				"instrument":"Astrometric",
				"magnitude":"17.38",
				"telescope":"GAIA",
				"u_time":"MJD",
				"source":"2"
			},
			{
				"time":"59602.10406",
				"band":"G",
				"e_magnitude":"0.0",
				"instrument":"Astrometric",
				"magnitude":"17.35",
				"telescope":"GAIA",
				"u_time":"MJD",
				"source":"2"
			},
			{
				"time":"59602.17806",
				"band":"G",
				"e_magnitude":"0.0",
				"instrument":"Astrometric",
				"magnitude":"17.36",
				"telescope":"GAIA",
				"u_time":"MJD",
				"source":"2"
			},
			{
				"time":"59627.84398",
				"band":"G",
				"e_magnitude":"0.0",
				"instrument":"Astrometric",
				"magnitude":"17.33",
				"telescope":"GAIA",
				"u_time":"MJD",
				"source":"2"
			},
			{
				"time":"59627.91799",
				"band":"G",
				"e_magnitude":"0.0",
				"instrument":"Astrometric",
				"magnitude":"17.33",
				"telescope":"GAIA",
				"u_time":"MJD",
				"source":"2"
			}
		]
	}
}