{
	"AT2018ing":{
		"schema":"https://github.com/astrocatalogs/supernovae/blob/d3ef5fc/SCHEMA.md",
		"name":"AT2018ing",
		"sources":[
			{
				"name":"Transient Name Server",
				"url":"https://www.wis-tns.org/object/2018ing",
				"alias":"1"
			},
			{
				"name":"Gaia Photometric Science Alerts",
				"url":"http://gsaweb.ast.cam.ac.uk/alerts/alertsindex",
				"alias":"2"
			},
			{
				"name":"Latest Supernovae",
				"secondary":true,
				"url":"http://www.rochesterastronomy.org/snimages/snredshiftall.html",
				"alias":"3"
			},
			{
				"name":"The Open Supernova Catalog",
				"bibcode":"2017ApJ...835...64G",
				"reference":"Guillochon et al. (2017)",
				"secondary":true,
				"url":"https://sne.space",
				"alias":"4"
			}
		],
		"alias":[
			{
				"value":"AT2018ing",
				"source":"1,2,3"
			},
			{
				"value":"ZTF18acmwuum",
				"source":"1,3"
			},
			{
				"value":"Gaia21cys",
				"source":"1,3"
			}
		],
		"claimedtype":[
			{
				"value":"CV",
				"source":"1,3"
			}
		],
		"dec":[
			{
				"value":"+47:10:24.09",
				"u_value":"degrees",
				"source":"1,3"
			},
			{
				"value":"+47:10:24.24",
				"u_value":"degrees",
				"source":"2"
			}
		],
		"discoverdate":[
			{
				"value":"2018/11/03",
				"source":"1,3"
			}
		],
		"discoverer":[
			{
				"value":"ZTF",
				"source":"1,3"
			}
		],
		"maxappmag":[
			{
				"value":"17.78",
				"derived":true,
				"source":"2,4"
			}
		],
		"maxband":[
			{
				"value":"G",
				"derived":true,
				"source":"2,4"
			}
		],
		"maxdate":[
			{
				"value":"2021/09/20",
				"derived":true,
				"source":"2,4"
			}
		],
		"maxvisualappmag":[
			{
				"value":"17.78",
				"derived":true,
				"source":"2,4"
			}
		],
		"maxvisualband":[
			{
				"value":"G",
				"derived":true,
				"source":"2,4"
			}
		],
		"maxvisualdate":[
			{
				"value":"2021/09/20",
				"derived":true,
				"source":"2,4"
			}
		],
		"ra":[
			{
				"value":"02:23:39.665",
				"u_value":"hours",
				"source":"1,3"
			},
			{
				"value":"02:23:39.672",
				"u_value":"hours",
				"source":"2"
			}
		],
		"photometry":[
			{
				"time":"57401.43439",
				"band":"G",
				"e_magnitude":"0.0",
				"instrument":"Astrometric",
				"magnitude":"21.07",
				"telescope":"GAIA",
				"u_time":"MJD",
				"source":"2"
			},
			{
				"time":"57453.33943",
				"band":"G",
				"e_magnitude":"0.0",
				"instrument":"Astrometric",
				"magnitude":"19.70",
				"telescope":"GAIA",
				"u_time":"MJD",
				"source":"2"
			},
			{
				"time":"57453.41343",
				"band":"G",
				"e_magnitude":"0.0",
				"instrument":"Astrometric",
				"magnitude":"19.65",
				"telescope":"GAIA",
				"u_time":"MJD",
				"source":"2"
			},
			{
				"time":"57829.19468",
				"band":"G",
				"e_magnitude":"0.0",
				"instrument":"Astrometric",
				"magnitude":"20.25",
				"telescope":"GAIA",
				"u_time":"MJD",
				"source":"2"
			},
			{
				"time":"57954.76963",
				"band":"G",
				"e_magnitude":"0.0",
				"instrument":"Astrometric",
				"magnitude":"20.91",
				"telescope":"GAIA",
				"u_time":"MJD",
				"source":"2"
			},
			{
				"time":"58653.80204",
				"band":"G",
				"e_magnitude":"0.0",
				"instrument":"Astrometric",
				"magnitude":"20.57",
				"telescope":"GAIA",
				"u_time":"MJD",
				"source":"2"
			},
			{
				"time":"58754.51066",
				"band":"G",
				"e_magnitude":"0.0",
				"instrument":"Astrometric",
				"magnitude":"21.05",
				"telescope":"GAIA",
				"u_time":"MJD",
				"source":"2"
			},
			{
				"time":"59224.41112",
				"band":"G",
				"e_magnitude":"0.0",
				"instrument":"Astrometric",
				"magnitude":"20.37",
				"telescope":"GAIA",
				"u_time":"MJD",
				"source":"2"
			},
			{
				"time":"59224.58727",
				"band":"G",
				"e_magnitude":"0.0",
				"instrument":"Astrometric",
				"magnitude":"20.52",
				"telescope":"GAIA",
				"u_time":"MJD",
				"source":"2"
			},
			{
				"time":"59298.85630",
				"band":"G",
				"e_magnitude":"0.0",
				"instrument":"Astrometric",
				"magnitude":"20.12",
				"telescope":"GAIA",
				"u_time":"MJD",
				"source":"2"
			},
			{
				"time":"59299.03244",
				"band":"G",
				"e_magnitude":"0.0",
				"instrument":"Astrometric",
				"magnitude":"20.25",
				"telescope":"GAIA",
				"u_time":"MJD",
				"source":"2"
			},
			{
				"time":"59299.10644",
				"band":"G",
				"e_magnitude":"0.0",
				"instrument":"Astrometric",
				"magnitude":"20.25",
				"telescope":"GAIA",
				"u_time":"MJD",
				"source":"2"
			},
			{
				"time":"59299.28258",
				"band":"G",
				"e_magnitude":"0.0",
				"instrument":"Astrometric",
				"magnitude":"20.60",
				"telescope":"GAIA",
				"u_time":"MJD",
				"source":"2"
			},
			{
				"time":"59309.03752",
				"band":"G",
				"e_magnitude":"0.0",
				"instrument":"Astrometric",
				"magnitude":"20.54",
				"telescope":"GAIA",
				"u_time":"MJD",
				"source":"2"
			},
			{
				"time":"59309.11153",
				"band":"G",
				"e_magnitude":"0.0",
				"instrument":"Astrometric",
				"magnitude":"20.88",
				"telescope":"GAIA",
				"u_time":"MJD",
				"source":"2"
			},
			{
				"time":"59309.28769",
				"band":"G",
				"e_magnitude":"0.0",
				"instrument":"Astrometric",
				"magnitude":"20.57",
				"telescope":"GAIA",
				"u_time":"MJD",
				"source":"2"
			},
			{
				"time":"59384.87492",
				"band":"G",
				"e_magnitude":"0.0",
				"instrument":"Astrometric",
				"magnitude":"18.59",
				"telescope":"GAIA",
				"u_time":"MJD",
				"source":"2"
			},
			{
				"time":"59385.05109",
				"band":"G",
				"e_magnitude":"0.0",
				"instrument":"Astrometric",
				"magnitude":"18.76",
				"telescope":"GAIA",
				"u_time":"MJD",
				"source":"2"
			},
			{
				"time":"59385.12509",
				"band":"G",
				"e_magnitude":"0.0",
				"instrument":"Astrometric",
				"magnitude":"18.87",
				"telescope":"GAIA",
				"u_time":"MJD",
				"source":"2"
			},
			{
				"time":"59477.76424",
				"band":"G",
				"e_magnitude":"0.0",
				"instrument":"Astrometric",
				"magnitude":"17.78",
				"telescope":"GAIA",
				"u_time":"MJD",
				"source":"2"
			},
			{
				"time":"59477.83825",
				"band":"G",
				"e_magnitude":"0.0",
				"instrument":"Astrometric",
				"magnitude":"17.82",
				"telescope":"GAIA",
				"u_time":"MJD",
				"source":"2"
			}
		]
	}
}