{
	"AT2022adm":{
		"schema":"https://github.com/astrocatalogs/supernovae/blob/d3ef5fc/SCHEMA.md",
		"name":"AT2022adm",
		"sources":[
			{
				"name":"2016A&A...594A..13P",
				"bibcode":"2016A&A...594A..13P",
				"reference":"Planck Collaboration et al. (2016)",
				"alias":"1"
			},
			{
				"name":"Transient Name Server",
				"url":"http://www.wis-tns.org/search",
				"alias":"2"
			},
			{
				"name":"Latest Supernovae",
				"secondary":true,
				"url":"http://www.rochesterastronomy.org/snimages/snredshiftall.html",
				"alias":"3"
			},
			{
				"name":"The Open Supernova Catalog",
				"bibcode":"2017ApJ...835...64G",
				"reference":"Guillochon et al. (2017)",
				"secondary":true,
				"url":"https://sne.space",
				"alias":"4"
			}
		],
		"alias":[
			{
				"value":"AT2022adm",
				"source":"2,3"
			},
			{
				"value":"ZTF22aaaekqh",
				"source":"2,3"
			}
		],
		"claimedtype":[
			{
				"value":"TDE",
				"source":"2,3"
			}
		],
		"comovingdist":[
			{
				"value":"270",
				"derived":true,
				"u_value":"Mpc",
				"source":"1,2,3,4"
			}
		],
		"dec":[
			{
				"value":"+28:10:29.03",
				"u_value":"degrees",
				"source":"2,3"
			}
		],
		"discoverdate":[
			{
				"value":"2022/01/16",
				"source":"2,3"
			}
		],
		"discoverer":[
			{
				"value":"ZTF",
				"source":"2,3"
			}
		],
		"host":[
			{
				"value":"SDSS J142751.44+281029.1",
				"source":"2,3"
			}
		],
		"hostdec":[
			{
				"value":"+28:10:29.1",
				"derived":true,
				"u_value":"degrees",
				"source":"4"
			}
		],
		"hostoffsetang":[
			{
				"value":"0.07124",
				"derived":true,
				"u_value":"arcseconds",
				"source":"2,3,4"
			}
		],
		"hostoffsetdist":[
			{
				"value":"0.08789",
				"source":"1,2,3,4"
			}
		],
		"hostra":[
			{
				"value":"14:27:51.44",
				"derived":true,
				"u_value":"hours",
				"source":"4"
			}
		],
		"lumdist":[
			{
				"value":"282",
				"derived":true,
				"u_value":"Mpc",
				"source":"1,2,3,4"
			}
		],
		"maxabsmag":[
			{
				"value":"-19.6",
				"derived":true,
				"source":"1,2,3,4"
			}
		],
		"maxappmag":[
			{
				"value":"17.6",
				"derived":true,
				"source":"2,3,4"
			}
		],
		"maxdate":[
			{
				"value":"2022/01/16",
				"derived":true,
				"source":"2,3,4"
			}
		],
		"maxvisualabsmag":[
			{
				"value":"-19.7",
				"derived":true,
				"source":"1,2,3,4"
			}
		],
		"maxvisualappmag":[
			{
				"value":"17.6",
				"derived":true,
				"source":"2,3,4"
			}
		],
		"maxvisualdate":[
			{
				"value":"2022/01/16",
				"derived":true,
				"source":"2,3,4"
			}
		],
		"ra":[
			{
				"value":"14:27:51.439",
				"u_value":"hours",
				"source":"2,3"
			}
		],
		"redshift":[
			{
				"value":"0.061",
				"source":"2,3"
			}
		],
		"velocity":[
			{
				"value":"18000",
				"u_value":"km/s",
				"source":"4"
			}
		],
		"photometry":[
			{
				"time":"59595.0",
				"magnitude":"17.6",
				"u_time":"MJD",
				"source":"2,3"
			}
		]
	}
}