{
	"AT2022dms":{
		"schema":"https://github.com/astrocatalogs/supernovae/blob/d3ef5fc/SCHEMA.md",
		"name":"AT2022dms",
		"sources":[
			{
				"name":"Transient Name Server",
				"url":"https://www.wis-tns.org/object/2022dms",
				"alias":"1"
			},
			{
				"name":"Gaia Photometric Science Alerts",
				"url":"http://gsaweb.ast.cam.ac.uk/alerts/alertsindex",
				"alias":"2"
			},
			{
				"name":"Latest Supernovae",
				"secondary":true,
				"url":"http://www.rochesterastronomy.org/snimages/snredshiftall.html",
				"alias":"3"
			},
			{
				"name":"The Open Supernova Catalog",
				"bibcode":"2017ApJ...835...64G",
				"reference":"Guillochon et al. (2017)",
				"secondary":true,
				"url":"https://sne.space",
				"alias":"4"
			}
		],
		"alias":[
			{
				"value":"AT2022dms",
				"source":"1,2,3"
			},
			{
				"value":"ZTF19aascawm",
				"source":"1,3"
			},
			{
				"value":"Gaia22bdr",
				"source":"1,3"
			}
		],
		"claimedtype":[
			{
				"value":"QSO",
				"source":"1,2,3"
			}
		],
		"dec":[
			{
				"value":"+51:17:42.89",
				"u_value":"degrees",
				"source":"1,3"
			},
			{
				"value":"+51:17:42.97",
				"u_value":"degrees",
				"source":"1,3"
			},
			{
				"value":"+51:17:43.08",
				"u_value":"degrees",
				"source":"2"
			}
		],
		"discoverdate":[
			{
				"value":"2022/02/26",
				"source":"1,3"
			}
		],
		"discoverer":[
			{
				"value":"ZTF",
				"source":"1,3"
			}
		],
		"maxappmag":[
			{
				"value":"18.18",
				"derived":true,
				"source":"2,4"
			}
		],
		"maxband":[
			{
				"value":"G",
				"derived":true,
				"source":"2,4"
			}
		],
		"maxdate":[
			{
				"value":"2022/03/17",
				"derived":true,
				"source":"2,4"
			}
		],
		"maxvisualappmag":[
			{
				"value":"18.18",
				"derived":true,
				"source":"2,4"
			}
		],
		"maxvisualband":[
			{
				"value":"G",
				"derived":true,
				"source":"2,4"
			}
		],
		"maxvisualdate":[
			{
				"value":"2022/03/17",
				"derived":true,
				"source":"2,4"
			}
		],
		"ra":[
			{
				"value":"13:21:38.323",
				"u_value":"hours",
				"source":"1,3"
			},
			{
				"value":"13:21:38.4",
				"u_value":"hours",
				"source":"2"
			}
		],
		"photometry":[
			{
				"time":"56865.00034",
				"band":"G",
				"e_magnitude":"0.0",
				"instrument":"Astrometric",
				"magnitude":"18.75",
				"telescope":"GAIA",
				"u_time":"MJD",
				"source":"2"
			},
			{
				"time":"56865.25049",
				"band":"G",
				"e_magnitude":"0.0",
				"instrument":"Astrometric",
				"magnitude":"18.70",
				"telescope":"GAIA",
				"u_time":"MJD",
				"source":"2"
			},
			{
				"time":"56865.50065",
				"band":"G",
				"e_magnitude":"0.0",
				"instrument":"Astrometric",
				"magnitude":"18.75",
				"telescope":"GAIA",
				"u_time":"MJD",
				"source":"2"
			},
			{
				"time":"56865.57464",
				"band":"G",
				"e_magnitude":"0.0",
				"instrument":"Astrometric",
				"magnitude":"18.72",
				"telescope":"GAIA",
				"u_time":"MJD",
				"source":"2"
			},
			{
				"time":"56865.75080",
				"band":"G",
				"e_magnitude":"0.0",
				"instrument":"Astrometric",
				"magnitude":"18.75",
				"telescope":"GAIA",
				"u_time":"MJD",
				"source":"2"
			},
			{
				"time":"56865.82480",
				"band":"G",
				"e_magnitude":"0.0",
				"instrument":"Astrometric",
				"magnitude":"18.67",
				"telescope":"GAIA",
				"u_time":"MJD",
				"source":"2"
			},
			{
				"time":"56866.00095",
				"band":"G",
				"e_magnitude":"0.0",
				"instrument":"Astrometric",
				"magnitude":"18.73",
				"telescope":"GAIA",
				"u_time":"MJD",
				"source":"2"
			},
			{
				"time":"56866.32512",
				"band":"G",
				"e_magnitude":"0.0",
				"instrument":"Astrometric",
				"magnitude":"18.70",
				"telescope":"GAIA",
				"u_time":"MJD",
				"source":"2"
			},
			{
				"time":"56898.59918",
				"band":"G",
				"e_magnitude":"0.0",
				"instrument":"Astrometric",
				"magnitude":"18.81",
				"telescope":"GAIA",
				"u_time":"MJD",
				"source":"2"
			},
			{
				"time":"56898.84934",
				"band":"G",
				"e_magnitude":"0.0",
				"instrument":"Astrometric",
				"magnitude":"18.85",
				"telescope":"GAIA",
				"u_time":"MJD",
				"source":"2"
			},
			{
				"time":"56970.41563",
				"band":"G",
				"e_magnitude":"0.0",
				"instrument":"Astrometric",
				"magnitude":"18.62",
				"telescope":"GAIA",
				"u_time":"MJD",
				"source":"2"
			},
			{
				"time":"57037.87042",
				"band":"G",
				"e_magnitude":"0.0",
				"instrument":"Astrometric",
				"magnitude":"18.75",
				"telescope":"GAIA",
				"u_time":"MJD",
				"source":"2"
			},
			{
				"time":"57055.19616",
				"band":"G",
				"e_magnitude":"0.0",
				"instrument":"Astrometric",
				"magnitude":"18.87",
				"telescope":"GAIA",
				"u_time":"MJD",
				"source":"2"
			},
			{
				"time":"57097.81093",
				"band":"G",
				"e_magnitude":"0.0",
				"instrument":"Astrometric",
				"magnitude":"18.78",
				"telescope":"GAIA",
				"u_time":"MJD",
				"source":"2"
			},
			{
				"time":"57097.88493",
				"band":"G",
				"e_magnitude":"0.0",
				"instrument":"Astrometric",
				"magnitude":"18.80",
				"telescope":"GAIA",
				"u_time":"MJD",
				"source":"2"
			},
			{
				"time":"57109.81520",
				"band":"G",
				"e_magnitude":"0.0",
				"instrument":"Astrometric",
				"magnitude":"18.80",
				"telescope":"GAIA",
				"u_time":"MJD",
				"source":"2"
			},
			{
				"time":"57176.00604",
				"band":"G",
				"e_magnitude":"0.0",
				"instrument":"Astrometric",
				"magnitude":"18.80",
				"telescope":"GAIA",
				"u_time":"MJD",
				"source":"2"
			},
			{
				"time":"57209.48740",
				"band":"G",
				"e_magnitude":"0.0",
				"instrument":"Astrometric",
				"magnitude":"18.77",
				"telescope":"GAIA",
				"u_time":"MJD",
				"source":"2"
			},
			{
				"time":"57209.56140",
				"band":"G",
				"e_magnitude":"0.0",
				"instrument":"Astrometric",
				"magnitude":"18.74",
				"telescope":"GAIA",
				"u_time":"MJD",
				"source":"2"
			},
			{
				"time":"57273.80075",
				"band":"G",
				"e_magnitude":"0.0",
				"instrument":"Astrometric",
				"magnitude":"18.64",
				"telescope":"GAIA",
				"u_time":"MJD",
				"source":"2"
			},
			{
				"time":"57274.05091",
				"band":"G",
				"e_magnitude":"0.0",
				"instrument":"Astrometric",
				"magnitude":"18.58",
				"telescope":"GAIA",
				"u_time":"MJD",
				"source":"2"
			},
			{
				"time":"57321.96330",
				"band":"G",
				"e_magnitude":"0.0",
				"instrument":"Astrometric",
				"magnitude":"18.70",
				"telescope":"GAIA",
				"u_time":"MJD",
				"source":"2"
			},
			{
				"time":"57322.03731",
				"band":"G",
				"e_magnitude":"0.0",
				"instrument":"Astrometric",
				"magnitude":"18.68",
				"telescope":"GAIA",
				"u_time":"MJD",
				"source":"2"
			},
			{
				"time":"57349.95959",
				"band":"G",
				"e_magnitude":"0.0",
				"instrument":"Astrometric",
				"magnitude":"18.67",
				"telescope":"GAIA",
				"u_time":"MJD",
				"source":"2"
			},
			{
				"time":"57378.44909",
				"band":"G",
				"e_magnitude":"0.0",
				"instrument":"Astrometric",
				"magnitude":"18.72",
				"telescope":"GAIA",
				"u_time":"MJD",
				"source":"2"
			},
			{
				"time":"57378.52309",
				"band":"G",
				"e_magnitude":"0.0",
				"instrument":"Astrometric",
				"magnitude":"18.66",
				"telescope":"GAIA",
				"u_time":"MJD",
				"source":"2"
			},
			{
				"time":"57415.65995",
				"band":"G",
				"e_magnitude":"0.0",
				"instrument":"Astrometric",
				"magnitude":"18.66",
				"telescope":"GAIA",
				"u_time":"MJD",
				"source":"2"
			},
			{
				"time":"57415.73397",
				"band":"G",
				"e_magnitude":"0.0",
				"instrument":"Astrometric",
				"magnitude":"18.63",
				"telescope":"GAIA",
				"u_time":"MJD",
				"source":"2"
			},
			{
				"time":"57430.73736",
				"band":"G",
				"e_magnitude":"0.0",
				"instrument":"Astrometric",
				"magnitude":"18.62",
				"telescope":"GAIA",
				"u_time":"MJD",
				"source":"2"
			},
			{
				"time":"57473.84991",
				"band":"G",
				"e_magnitude":"0.0",
				"instrument":"Astrometric",
				"magnitude":"18.58",
				"telescope":"GAIA",
				"u_time":"MJD",
				"source":"2"
			},
			{
				"time":"57473.92391",
				"band":"G",
				"e_magnitude":"0.0",
				"instrument":"Astrometric",
				"magnitude":"18.59",
				"telescope":"GAIA",
				"u_time":"MJD",
				"source":"2"
			},
			{
				"time":"57487.35356",
				"band":"G",
				"e_magnitude":"0.0",
				"instrument":"Astrometric",
				"magnitude":"18.66",
				"telescope":"GAIA",
				"u_time":"MJD",
				"source":"2"
			},
			{
				"time":"57487.42757",
				"band":"G",
				"e_magnitude":"0.0",
				"instrument":"Astrometric",
				"magnitude":"18.64",
				"telescope":"GAIA",
				"u_time":"MJD",
				"source":"2"
			},
			{
				"time":"57555.54666",
				"band":"G",
				"e_magnitude":"0.0",
				"instrument":"Astrometric",
				"magnitude":"18.75",
				"telescope":"GAIA",
				"u_time":"MJD",
				"source":"2"
			},
			{
				"time":"57586.85916",
				"band":"G",
				"e_magnitude":"0.0",
				"instrument":"Astrometric",
				"magnitude":"18.56",
				"telescope":"GAIA",
				"u_time":"MJD",
				"source":"2"
			},
			{
				"time":"57633.34271",
				"band":"G",
				"e_magnitude":"0.0",
				"instrument":"Astrometric",
				"magnitude":"18.56",
				"telescope":"GAIA",
				"u_time":"MJD",
				"source":"2"
			},
			{
				"time":"57633.51887",
				"band":"G",
				"e_magnitude":"0.0",
				"instrument":"Astrometric",
				"magnitude":"18.52",
				"telescope":"GAIA",
				"u_time":"MJD",
				"source":"2"
			},
			{
				"time":"57633.59288",
				"band":"G",
				"e_magnitude":"0.0",
				"instrument":"Astrometric",
				"magnitude":"18.55",
				"telescope":"GAIA",
				"u_time":"MJD",
				"source":"2"
			},
			{
				"time":"57633.76903",
				"band":"G",
				"e_magnitude":"0.0",
				"instrument":"Astrometric",
				"magnitude":"18.53",
				"telescope":"GAIA",
				"u_time":"MJD",
				"source":"2"
			},
			{
				"time":"57654.02671",
				"band":"G",
				"e_magnitude":"0.0",
				"instrument":"Astrometric",
				"magnitude":"18.51",
				"telescope":"GAIA",
				"u_time":"MJD",
				"source":"2"
			},
			{
				"time":"57654.27688",
				"band":"G",
				"e_magnitude":"0.0",
				"instrument":"Astrometric",
				"magnitude":"18.50",
				"telescope":"GAIA",
				"u_time":"MJD",
				"source":"2"
			},
			{
				"time":"57654.35088",
				"band":"G",
				"e_magnitude":"0.0",
				"instrument":"Astrometric",
				"magnitude":"18.52",
				"telescope":"GAIA",
				"u_time":"MJD",
				"source":"2"
			},
			{
				"time":"57699.01226",
				"band":"G",
				"e_magnitude":"0.0",
				"instrument":"Astrometric",
				"magnitude":"18.58",
				"telescope":"GAIA",
				"u_time":"MJD",
				"source":"2"
			},
			{
				"time":"57754.49516",
				"band":"G",
				"e_magnitude":"0.0",
				"instrument":"Astrometric",
				"magnitude":"18.63",
				"telescope":"GAIA",
				"u_time":"MJD",
				"source":"2"
			},
			{
				"time":"57793.50657",
				"band":"G",
				"e_magnitude":"0.0",
				"instrument":"Astrometric",
				"magnitude":"18.60",
				"telescope":"GAIA",
				"u_time":"MJD",
				"source":"2"
			},
			{
				"time":"57806.33462",
				"band":"G",
				"e_magnitude":"0.0",
				"instrument":"Astrometric",
				"magnitude":"18.64",
				"telescope":"GAIA",
				"u_time":"MJD",
				"source":"2"
			},
			{
				"time":"57806.51078",
				"band":"G",
				"e_magnitude":"0.0",
				"instrument":"Astrometric",
				"magnitude":"18.66",
				"telescope":"GAIA",
				"u_time":"MJD",
				"source":"2"
			},
			{
				"time":"57849.69701",
				"band":"G",
				"e_magnitude":"0.0",
				"instrument":"Astrometric",
				"magnitude":"18.67",
				"telescope":"GAIA",
				"u_time":"MJD",
				"source":"2"
			},
			{
				"time":"57849.77102",
				"band":"G",
				"e_magnitude":"0.0",
				"instrument":"Astrometric",
				"magnitude":"18.71",
				"telescope":"GAIA",
				"u_time":"MJD",
				"source":"2"
			},
			{
				"time":"57865.52347",
				"band":"G",
				"e_magnitude":"0.0",
				"instrument":"Astrometric",
				"magnitude":"18.67",
				"telescope":"GAIA",
				"u_time":"MJD",
				"source":"2"
			},
			{
				"time":"57904.65883",
				"band":"G",
				"e_magnitude":"0.0",
				"instrument":"Astrometric",
				"magnitude":"18.62",
				"telescope":"GAIA",
				"u_time":"MJD",
				"source":"2"
			},
			{
				"time":"57935.39558",
				"band":"G",
				"e_magnitude":"0.0",
				"instrument":"Astrometric",
				"magnitude":"18.69",
				"telescope":"GAIA",
				"u_time":"MJD",
				"source":"2"
			},
			{
				"time":"57935.46958",
				"band":"G",
				"e_magnitude":"0.0",
				"instrument":"Astrometric",
				"magnitude":"18.62",
				"telescope":"GAIA",
				"u_time":"MJD",
				"source":"2"
			},
			{
				"time":"57964.39073",
				"band":"G",
				"e_magnitude":"0.0",
				"instrument":"Astrometric",
				"magnitude":"18.67",
				"telescope":"GAIA",
				"u_time":"MJD",
				"source":"2"
			},
			{
				"time":"57964.46473",
				"band":"G",
				"e_magnitude":"0.0",
				"instrument":"Astrometric",
				"magnitude":"18.60",
				"telescope":"GAIA",
				"u_time":"MJD",
				"source":"2"
			},
			{
				"time":"58013.70006",
				"band":"G",
				"e_magnitude":"0.0",
				"instrument":"Astrometric",
				"magnitude":"18.65",
				"telescope":"GAIA",
				"u_time":"MJD",
				"source":"2"
			},
			{
				"time":"58013.87622",
				"band":"G",
				"e_magnitude":"0.0",
				"instrument":"Astrometric",
				"magnitude":"18.63",
				"telescope":"GAIA",
				"u_time":"MJD",
				"source":"2"
			},
			{
				"time":"58013.95022",
				"band":"G",
				"e_magnitude":"0.0",
				"instrument":"Astrometric",
				"magnitude":"18.66",
				"telescope":"GAIA",
				"u_time":"MJD",
				"source":"2"
			},
			{
				"time":"58014.12638",
				"band":"G",
				"e_magnitude":"0.0",
				"instrument":"Astrometric",
				"magnitude":"18.67",
				"telescope":"GAIA",
				"u_time":"MJD",
				"source":"2"
			},
			{
				"time":"58035.38362",
				"band":"G",
				"e_magnitude":"0.0",
				"instrument":"Astrometric",
				"magnitude":"18.59",
				"telescope":"GAIA",
				"u_time":"MJD",
				"source":"2"
			},
			{
				"time":"58035.45763",
				"band":"G",
				"e_magnitude":"0.0",
				"instrument":"Astrometric",
				"magnitude":"18.61",
				"telescope":"GAIA",
				"u_time":"MJD",
				"source":"2"
			},
			{
				"time":"58035.63380",
				"band":"G",
				"e_magnitude":"0.0",
				"instrument":"Astrometric",
				"magnitude":"18.59",
				"telescope":"GAIA",
				"u_time":"MJD",
				"source":"2"
			},
			{
				"time":"58035.70780",
				"band":"G",
				"e_magnitude":"0.0",
				"instrument":"Astrometric",
				"magnitude":"18.64",
				"telescope":"GAIA",
				"u_time":"MJD",
				"source":"2"
			},
			{
				"time":"58075.69204",
				"band":"G",
				"e_magnitude":"0.0",
				"instrument":"Astrometric",
				"magnitude":"18.67",
				"telescope":"GAIA",
				"u_time":"MJD",
				"source":"2"
			},
			{
				"time":"58107.67506",
				"band":"G",
				"e_magnitude":"0.0",
				"instrument":"Astrometric",
				"magnitude":"18.76",
				"telescope":"GAIA",
				"u_time":"MJD",
				"source":"2"
			},
			{
				"time":"58130.17133",
				"band":"G",
				"e_magnitude":"0.0",
				"instrument":"Astrometric",
				"magnitude":"18.67",
				"telescope":"GAIA",
				"u_time":"MJD",
				"source":"2"
			},
			{
				"time":"58182.29972",
				"band":"G",
				"e_magnitude":"0.0",
				"instrument":"Astrometric",
				"magnitude":"18.68",
				"telescope":"GAIA",
				"u_time":"MJD",
				"source":"2"
			},
			{
				"time":"58182.37374",
				"band":"G",
				"e_magnitude":"0.0",
				"instrument":"Astrometric",
				"magnitude":"18.65",
				"telescope":"GAIA",
				"u_time":"MJD",
				"source":"2"
			},
			{
				"time":"58225.56190",
				"band":"G",
				"e_magnitude":"0.0",
				"instrument":"Astrometric",
				"magnitude":"18.60",
				"telescope":"GAIA",
				"u_time":"MJD",
				"source":"2"
			},
			{
				"time":"58244.06238",
				"band":"G",
				"e_magnitude":"0.0",
				"instrument":"Astrometric",
				"magnitude":"18.60",
				"telescope":"GAIA",
				"u_time":"MJD",
				"source":"2"
			},
			{
				"time":"58281.45490",
				"band":"G",
				"e_magnitude":"0.0",
				"instrument":"Astrometric",
				"magnitude":"18.60",
				"telescope":"GAIA",
				"u_time":"MJD",
				"source":"2"
			},
			{
				"time":"58281.52890",
				"band":"G",
				"e_magnitude":"0.0",
				"instrument":"Astrometric",
				"magnitude":"18.62",
				"telescope":"GAIA",
				"u_time":"MJD",
				"source":"2"
			},
			{
				"time":"58315.76266",
				"band":"G",
				"e_magnitude":"0.0",
				"instrument":"Astrometric",
				"magnitude":"18.65",
				"telescope":"GAIA",
				"u_time":"MJD",
				"source":"2"
			},
			{
				"time":"58315.93881",
				"band":"G",
				"e_magnitude":"0.0",
				"instrument":"Astrometric",
				"magnitude":"18.67",
				"telescope":"GAIA",
				"u_time":"MJD",
				"source":"2"
			},
			{
				"time":"58342.51353",
				"band":"G",
				"e_magnitude":"0.0",
				"instrument":"Astrometric",
				"magnitude":"18.52",
				"telescope":"GAIA",
				"u_time":"MJD",
				"source":"2"
			},
			{
				"time":"58392.75000",
				"band":"G",
				"e_magnitude":"0.0",
				"instrument":"Astrometric",
				"magnitude":"18.60",
				"telescope":"GAIA",
				"u_time":"MJD",
				"source":"2"
			},
			{
				"time":"58392.92616",
				"band":"G",
				"e_magnitude":"0.0",
				"instrument":"Astrometric",
				"magnitude":"18.60",
				"telescope":"GAIA",
				"u_time":"MJD",
				"source":"2"
			},
			{
				"time":"58416.43147",
				"band":"G",
				"e_magnitude":"0.0",
				"instrument":"Astrometric",
				"magnitude":"18.66",
				"telescope":"GAIA",
				"u_time":"MJD",
				"source":"2"
			},
			{
				"time":"58416.50549",
				"band":"G",
				"e_magnitude":"0.0",
				"instrument":"Astrometric",
				"magnitude":"18.71",
				"telescope":"GAIA",
				"u_time":"MJD",
				"source":"2"
			},
			{
				"time":"58452.24019",
				"band":"G",
				"e_magnitude":"0.0",
				"instrument":"Astrometric",
				"magnitude":"18.69",
				"telescope":"GAIA",
				"u_time":"MJD",
				"source":"2"
			},
			{
				"time":"58485.89178",
				"band":"G",
				"e_magnitude":"0.0",
				"instrument":"Astrometric",
				"magnitude":"18.68",
				"telescope":"GAIA",
				"u_time":"MJD",
				"source":"2"
			},
			{
				"time":"58485.96579",
				"band":"G",
				"e_magnitude":"0.0",
				"instrument":"Astrometric",
				"magnitude":"18.71",
				"telescope":"GAIA",
				"u_time":"MJD",
				"source":"2"
			},
			{
				"time":"58505.89125",
				"band":"G",
				"e_magnitude":"0.0",
				"instrument":"Astrometric",
				"magnitude":"18.67",
				"telescope":"GAIA",
				"u_time":"MJD",
				"source":"2"
			},
			{
				"time":"58505.96527",
				"band":"G",
				"e_magnitude":"0.0",
				"instrument":"Astrometric",
				"magnitude":"18.70",
				"telescope":"GAIA",
				"u_time":"MJD",
				"source":"2"
			},
			{
				"time":"58547.58390",
				"band":"G",
				"e_magnitude":"0.0",
				"instrument":"Astrometric",
				"magnitude":"18.65",
				"telescope":"GAIA",
				"u_time":"MJD",
				"source":"2"
			},
			{
				"time":"58547.65791",
				"band":"G",
				"e_magnitude":"0.0",
				"instrument":"Astrometric",
				"magnitude":"18.60",
				"telescope":"GAIA",
				"u_time":"MJD",
				"source":"2"
			},
			{
				"time":"58558.83832",
				"band":"G",
				"e_magnitude":"0.0",
				"instrument":"Astrometric",
				"magnitude":"18.67",
				"telescope":"GAIA",
				"u_time":"MJD",
				"source":"2"
			},
			{
				"time":"58558.91233",
				"band":"G",
				"e_magnitude":"0.0",
				"instrument":"Astrometric",
				"magnitude":"18.65",
				"telescope":"GAIA",
				"u_time":"MJD",
				"source":"2"
			},
			{
				"time":"58601.53007",
				"band":"G",
				"e_magnitude":"0.0",
				"instrument":"Astrometric",
				"magnitude":"18.67",
				"telescope":"GAIA",
				"u_time":"MJD",
				"source":"2"
			},
			{
				"time":"58601.60407",
				"band":"G",
				"e_magnitude":"0.0",
				"instrument":"Astrometric",
				"magnitude":"18.71",
				"telescope":"GAIA",
				"u_time":"MJD",
				"source":"2"
			},
			{
				"time":"58623.02779",
				"band":"G",
				"e_magnitude":"0.0",
				"instrument":"Astrometric",
				"magnitude":"18.70",
				"telescope":"GAIA",
				"u_time":"MJD",
				"source":"2"
			},
			{
				"time":"58658.50167",
				"band":"G",
				"e_magnitude":"0.0",
				"instrument":"Astrometric",
				"magnitude":"18.77",
				"telescope":"GAIA",
				"u_time":"MJD",
				"source":"2"
			},
			{
				"time":"58658.57567",
				"band":"G",
				"e_magnitude":"0.0",
				"instrument":"Astrometric",
				"magnitude":"18.74",
				"telescope":"GAIA",
				"u_time":"MJD",
				"source":"2"
			},
			{
				"time":"58690.57037",
				"band":"G",
				"e_magnitude":"0.0",
				"instrument":"Astrometric",
				"magnitude":"18.67",
				"telescope":"GAIA",
				"u_time":"MJD",
				"source":"2"
			},
			{
				"time":"58690.64438",
				"band":"G",
				"e_magnitude":"0.0",
				"instrument":"Astrometric",
				"magnitude":"18.68",
				"telescope":"GAIA",
				"u_time":"MJD",
				"source":"2"
			},
			{
				"time":"58734.43447",
				"band":"G",
				"e_magnitude":"0.0",
				"instrument":"Astrometric",
				"magnitude":"18.62",
				"telescope":"GAIA",
				"u_time":"MJD",
				"source":"2"
			},
			{
				"time":"58734.50847",
				"band":"G",
				"e_magnitude":"0.0",
				"instrument":"Astrometric",
				"magnitude":"18.60",
				"telescope":"GAIA",
				"u_time":"MJD",
				"source":"2"
			},
			{
				"time":"58734.68464",
				"band":"G",
				"e_magnitude":"0.0",
				"instrument":"Astrometric",
				"magnitude":"18.57",
				"telescope":"GAIA",
				"u_time":"MJD",
				"source":"2"
			},
			{
				"time":"58745.94508",
				"band":"G",
				"e_magnitude":"0.0",
				"instrument":"Astrometric",
				"magnitude":"18.56",
				"telescope":"GAIA",
				"u_time":"MJD",
				"source":"2"
			},
			{
				"time":"58746.01909",
				"band":"G",
				"e_magnitude":"0.0",
				"instrument":"Astrometric",
				"magnitude":"18.58",
				"telescope":"GAIA",
				"u_time":"MJD",
				"source":"2"
			},
			{
				"time":"58788.55921",
				"band":"G",
				"e_magnitude":"0.0",
				"instrument":"Astrometric",
				"magnitude":"18.48",
				"telescope":"GAIA",
				"u_time":"MJD",
				"source":"2"
			},
			{
				"time":"58809.33968",
				"band":"G",
				"e_magnitude":"0.0",
				"instrument":"Astrometric",
				"magnitude":"18.54",
				"telescope":"GAIA",
				"u_time":"MJD",
				"source":"2"
			},
			{
				"time":"58842.66042",
				"band":"G",
				"e_magnitude":"0.0",
				"instrument":"Astrometric",
				"magnitude":"18.61",
				"telescope":"GAIA",
				"u_time":"MJD",
				"source":"2"
			},
			{
				"time":"58878.72743",
				"band":"G",
				"e_magnitude":"0.0",
				"instrument":"Astrometric",
				"magnitude":"18.66",
				"telescope":"GAIA",
				"u_time":"MJD",
				"source":"2"
			},
			{
				"time":"58878.80144",
				"band":"G",
				"e_magnitude":"0.0",
				"instrument":"Astrometric",
				"magnitude":"18.66",
				"telescope":"GAIA",
				"u_time":"MJD",
				"source":"2"
			},
			{
				"time":"58901.32688",
				"band":"G",
				"e_magnitude":"0.0",
				"instrument":"Astrometric",
				"magnitude":"18.66",
				"telescope":"GAIA",
				"u_time":"MJD",
				"source":"2"
			},
			{
				"time":"58901.50303",
				"band":"G",
				"e_magnitude":"0.0",
				"instrument":"Astrometric",
				"magnitude":"18.63",
				"telescope":"GAIA",
				"u_time":"MJD",
				"source":"2"
			},
			{
				"time":"58901.57704",
				"band":"G",
				"e_magnitude":"0.0",
				"instrument":"Astrometric",
				"magnitude":"18.65",
				"telescope":"GAIA",
				"u_time":"MJD",
				"source":"2"
			},
			{
				"time":"58950.33119",
				"band":"G",
				"e_magnitude":"0.0",
				"instrument":"Astrometric",
				"magnitude":"18.73",
				"telescope":"GAIA",
				"u_time":"MJD",
				"source":"2"
			},
			{
				"time":"58950.58134",
				"band":"G",
				"e_magnitude":"0.0",
				"instrument":"Astrometric",
				"magnitude":"18.74",
				"telescope":"GAIA",
				"u_time":"MJD",
				"source":"2"
			},
			{
				"time":"58977.11471",
				"band":"G",
				"e_magnitude":"0.0",
				"instrument":"Astrometric",
				"magnitude":"18.47",
				"telescope":"GAIA",
				"u_time":"MJD",
				"source":"2"
			},
			{
				"time":"58977.18872",
				"band":"G",
				"e_magnitude":"0.0",
				"instrument":"Astrometric",
				"magnitude":"18.68",
				"telescope":"GAIA",
				"u_time":"MJD",
				"source":"2"
			},
			{
				"time":"59010.42067",
				"band":"G",
				"e_magnitude":"0.0",
				"instrument":"Astrometric",
				"magnitude":"18.58",
				"telescope":"GAIA",
				"u_time":"MJD",
				"source":"2"
			},
			{
				"time":"59010.49468",
				"band":"G",
				"e_magnitude":"0.0",
				"instrument":"Astrometric",
				"magnitude":"18.54",
				"telescope":"GAIA",
				"u_time":"MJD",
				"source":"2"
			},
			{
				"time":"59048.50147",
				"band":"G",
				"e_magnitude":"0.0",
				"instrument":"Astrometric",
				"magnitude":"18.59",
				"telescope":"GAIA",
				"u_time":"MJD",
				"source":"2"
			},
			{
				"time":"59048.57547",
				"band":"G",
				"e_magnitude":"0.0",
				"instrument":"Astrometric",
				"magnitude":"18.56",
				"telescope":"GAIA",
				"u_time":"MJD",
				"source":"2"
			},
			{
				"time":"59074.18883",
				"band":"G",
				"e_magnitude":"0.0",
				"instrument":"Astrometric",
				"magnitude":"18.57",
				"telescope":"GAIA",
				"u_time":"MJD",
				"source":"2"
			},
			{
				"time":"59074.26284",
				"band":"G",
				"e_magnitude":"0.0",
				"instrument":"Astrometric",
				"magnitude":"18.59",
				"telescope":"GAIA",
				"u_time":"MJD",
				"source":"2"
			},
			{
				"time":"59124.49936",
				"band":"G",
				"e_magnitude":"0.0",
				"instrument":"Astrometric",
				"magnitude":"18.54",
				"telescope":"GAIA",
				"u_time":"MJD",
				"source":"2"
			},
			{
				"time":"59124.67552",
				"band":"G",
				"e_magnitude":"0.0",
				"instrument":"Astrometric",
				"magnitude":"18.57",
				"telescope":"GAIA",
				"u_time":"MJD",
				"source":"2"
			},
			{
				"time":"59148.43059",
				"band":"G",
				"e_magnitude":"0.0",
				"instrument":"Astrometric",
				"magnitude":"18.50",
				"telescope":"GAIA",
				"u_time":"MJD",
				"source":"2"
			},
			{
				"time":"59148.50459",
				"band":"G",
				"e_magnitude":"0.0",
				"instrument":"Astrometric",
				"magnitude":"18.53",
				"telescope":"GAIA",
				"u_time":"MJD",
				"source":"2"
			},
			{
				"time":"59183.73933",
				"band":"G",
				"e_magnitude":"0.0",
				"instrument":"Astrometric",
				"magnitude":"18.55",
				"telescope":"GAIA",
				"u_time":"MJD",
				"source":"2"
			},
			{
				"time":"59183.91550",
				"band":"G",
				"e_magnitude":"0.0",
				"instrument":"Astrometric",
				"magnitude":"18.58",
				"telescope":"GAIA",
				"u_time":"MJD",
				"source":"2"
			},
			{
				"time":"59217.64029",
				"band":"G",
				"e_magnitude":"0.0",
				"instrument":"Astrometric",
				"magnitude":"18.59",
				"telescope":"GAIA",
				"u_time":"MJD",
				"source":"2"
			},
			{
				"time":"59217.71431",
				"band":"G",
				"e_magnitude":"0.0",
				"instrument":"Astrometric",
				"magnitude":"18.56",
				"telescope":"GAIA",
				"u_time":"MJD",
				"source":"2"
			},
			{
				"time":"59237.39002",
				"band":"G",
				"e_magnitude":"0.0",
				"instrument":"Astrometric",
				"magnitude":"18.49",
				"telescope":"GAIA",
				"u_time":"MJD",
				"source":"2"
			},
			{
				"time":"59279.15617",
				"band":"G",
				"e_magnitude":"0.0",
				"instrument":"Astrometric",
				"magnitude":"18.44",
				"telescope":"GAIA",
				"u_time":"MJD",
				"source":"2"
			},
			{
				"time":"59279.33233",
				"band":"G",
				"e_magnitude":"0.0",
				"instrument":"Astrometric",
				"magnitude":"18.41",
				"telescope":"GAIA",
				"u_time":"MJD",
				"source":"2"
			},
			{
				"time":"59290.33656",
				"band":"G",
				"e_magnitude":"0.0",
				"instrument":"Astrometric",
				"magnitude":"18.39",
				"telescope":"GAIA",
				"u_time":"MJD",
				"source":"2"
			},
			{
				"time":"59290.41057",
				"band":"G",
				"e_magnitude":"0.0",
				"instrument":"Astrometric",
				"magnitude":"18.36",
				"telescope":"GAIA",
				"u_time":"MJD",
				"source":"2"
			},
			{
				"time":"59354.77618",
				"band":"G",
				"e_magnitude":"0.0",
				"instrument":"Astrometric",
				"magnitude":"18.35",
				"telescope":"GAIA",
				"u_time":"MJD",
				"source":"2"
			},
			{
				"time":"59354.85019",
				"band":"G",
				"e_magnitude":"0.0",
				"instrument":"Astrometric",
				"magnitude":"18.33",
				"telescope":"GAIA",
				"u_time":"MJD",
				"source":"2"
			},
			{
				"time":"59390.07470",
				"band":"G",
				"e_magnitude":"0.0",
				"instrument":"Astrometric",
				"magnitude":"18.39",
				"telescope":"GAIA",
				"u_time":"MJD",
				"source":"2"
			},
			{
				"time":"59428.80679",
				"band":"G",
				"e_magnitude":"0.0",
				"instrument":"Astrometric",
				"magnitude":"18.24",
				"telescope":"GAIA",
				"u_time":"MJD",
				"source":"2"
			},
			{
				"time":"59428.98295",
				"band":"G",
				"e_magnitude":"0.0",
				"instrument":"Astrometric",
				"magnitude":"18.24",
				"telescope":"GAIA",
				"u_time":"MJD",
				"source":"2"
			},
			{
				"time":"59452.48795",
				"band":"G",
				"e_magnitude":"0.0",
				"instrument":"Astrometric",
				"magnitude":"18.31",
				"telescope":"GAIA",
				"u_time":"MJD",
				"source":"2"
			},
			{
				"time":"59452.56196",
				"band":"G",
				"e_magnitude":"0.0",
				"instrument":"Astrometric",
				"magnitude":"18.35",
				"telescope":"GAIA",
				"u_time":"MJD",
				"source":"2"
			},
			{
				"time":"59452.73811",
				"band":"G",
				"e_magnitude":"0.0",
				"instrument":"Astrometric",
				"magnitude":"18.35",
				"telescope":"GAIA",
				"u_time":"MJD",
				"source":"2"
			},
			{
				"time":"59452.81212",
				"band":"G",
				"e_magnitude":"0.0",
				"instrument":"Astrometric",
				"magnitude":"18.37",
				"telescope":"GAIA",
				"u_time":"MJD",
				"source":"2"
			},
			{
				"time":"59502.54897",
				"band":"G",
				"e_magnitude":"0.0",
				"instrument":"Astrometric",
				"magnitude":"18.30",
				"telescope":"GAIA",
				"u_time":"MJD",
				"source":"2"
			},
			{
				"time":"59528.47605",
				"band":"G",
				"e_magnitude":"0.0",
				"instrument":"Astrometric",
				"magnitude":"18.35",
				"telescope":"GAIA",
				"u_time":"MJD",
				"source":"2"
			},
			{
				"time":"59528.55007",
				"band":"G",
				"e_magnitude":"0.0",
				"instrument":"Astrometric",
				"magnitude":"18.36",
				"telescope":"GAIA",
				"u_time":"MJD",
				"source":"2"
			},
			{
				"time":"59560.21300",
				"band":"G",
				"e_magnitude":"0.0",
				"instrument":"Astrometric",
				"magnitude":"18.34",
				"telescope":"GAIA",
				"u_time":"MJD",
				"source":"2"
			},
			{
				"time":"59595.75436",
				"band":"G",
				"e_magnitude":"0.0",
				"instrument":"Astrometric",
				"magnitude":"18.35",
				"telescope":"GAIA",
				"u_time":"MJD",
				"source":"2"
			},
			{
				"time":"59612.93243",
				"band":"G",
				"e_magnitude":"0.0",
				"instrument":"Astrometric",
				"magnitude":"18.23",
				"telescope":"GAIA",
				"u_time":"MJD",
				"source":"2"
			},
			{
				"time":"59613.00644",
				"band":"G",
				"e_magnitude":"0.0",
				"instrument":"Astrometric",
				"magnitude":"18.22",
				"telescope":"GAIA",
				"u_time":"MJD",
				"source":"2"
			},
			{
				"time":"59655.62088",
				"band":"G",
				"e_magnitude":"0.0",
				"instrument":"Astrometric",
				"magnitude":"18.21",
				"telescope":"GAIA",
				"u_time":"MJD",
				"source":"2"
			},
			{
				"time":"59655.69488",
				"band":"G",
				"e_magnitude":"0.0",
				"instrument":"Astrometric",
				"magnitude":"18.18",
				"telescope":"GAIA",
				"u_time":"MJD",
				"source":"2"
			}
		]
	}
}