{
	"ESSENCEd123":{
		"schema":"https://github.com/astrocatalogs/supernovae/blob/a0bc0b9/SCHEMA.md",
		"name":"ESSENCEd123",
		"sources":[
			{
				"name":"2016ApJS..224....3N",
				"bibcode":"2016ApJS..224....3N",
				"reference":"Narayan et al. (2016)",
				"alias":"1"
			},
			{
				"name":"2016A&A...594A..13P",
				"bibcode":"2016A&A...594A..13P",
				"reference":"Planck Collaboration et al. (2016)",
				"alias":"2"
			},
			{
				"name":"2011ApJ...737..103S",
				"bibcode":"2011ApJ...737..103S",
				"reference":"Schlafly & Finkbeiner (2011)",
				"alias":"3"
			},
			{
				"name":"The Open Supernova Catalog",
				"bibcode":"2017ApJ...835...64G",
				"reference":"Guillochon et al. (2017)",
				"secondary":true,
				"url":"https://sne.space",
				"alias":"4"
			}
		],
		"alias":[
			{
				"value":"ESSENCEd123",
				"source":"1"
			}
		],
		"claimedtype":[
			{
				"value":"Galaxy",
				"source":"1"
			}
		],
		"comovingdist":[
			{
				"value":"1944",
				"derived":true,
				"u_value":"Mpc",
				"source":"1,2,4"
			}
		],
		"dec":[
			{
				"value":"-04:39:08.710",
				"u_value":"degrees",
				"source":"1"
			}
		],
		"discoverdate":[
			{
				"value":"2003/10/30",
				"derived":true,
				"source":"1,4"
			}
		],
		"ebv":[
			{
				"value":"0.0208",
				"derived":true,
				"e_value":"0.0006",
				"source":"3,4"
			}
		],
		"hostcomovingdist":[
			{
				"value":"1944",
				"derived":true,
				"source":"1,2,4"
			}
		],
		"hostlumdist":[
			{
				"value":"2914.8",
				"derived":true,
				"source":"1,2,4"
			}
		],
		"hostredshift":[
			{
				"value":"0.4995",
				"e_value":"0.0004",
				"source":"1"
			}
		],
		"hostvelocity":[
			{
				"value":"115200",
				"source":"4"
			}
		],
		"lumdist":[
			{
				"value":"2914.8",
				"derived":true,
				"u_value":"Mpc",
				"source":"1,2,4"
			}
		],
		"ra":[
			{
				"value":"02:06:08.565",
				"u_value":"hours",
				"source":"1"
			}
		],
		"redshift":[
			{
				"value":"0.4995",
				"e_value":"0.0004",
				"kind":"host",
				"source":"1"
			}
		],
		"velocity":[
			{
				"value":"115200",
				"u_value":"km/s",
				"source":"4"
			}
		],
		"spectra":[
			{
				"time":"52942.27",
				"filename":"d123_20031030.270_fors1.flm",
				"instrument":"FORS1",
				"telescope":"VLT",
				"u_fluxes":"erg/s/cm^2/Angstrom",
				"u_time":"MJD",
				"u_wavelengths":"Angstrom",
				"data":[
					[
						"4350.00",
						"2.35617e-18"
					],
					[
						"4352.65",
						"1.60668e-18"
					],
					[
						"4355.30",
						"1.81654e-18"
					],
					[
						"4357.95",
						"1.93403e-18"
					],
					[
						"4360.60",
						"2.14763e-18"
					],
					[
						"4363.25",
						"9.0666e-19"
					],
					[
						"4365.90",
						"2.06603e-18"
					],
					[
						"4368.55",
						"3.75352e-18"
					],
					[
						"4371.20",
						"1.73711e-18"
					],
					[
						"4373.85",
						"1.28861e-18"
					],
					[
						"4376.50",
						"1.11443e-18"
					],
					[
						"4379.15",
						"3.62515e-18"
					],
					[
						"4381.80",
						"2.46176e-18"
					],
					[
						"4384.45",
						"1.20311e-18"
					],
					[
						"4387.10",
						"1.36154e-18"
					],
					[
						"4389.75",
						"1.97038e-18"
					],
					[
						"4392.40",
						"3.42533e-18"
					],
					[
						"4395.05",
						"2.94628e-18"
					],
					[
						"4397.70",
						"1.61628e-18"
					],
					[
						"4400.35",
						"1.25428e-18"
					],
					[
						"4403.00",
						"1.71927e-18"
					],
					[
						"4405.65",
						"2.30035e-18"
					],
					[
						"4408.30",
						"2.05157e-18"
					],
					[
						"4410.95",
						"1.45639e-18"
					],
					[
						"4413.60",
						"2.7696e-18"
					],
					[
						"4416.25",
						"2.62432e-18"
					],
					[
						"4418.90",
						"3.22987e-18"
					],
					[
						"4421.55",
						"9.58598e-19"
					],
					[
						"4424.20",
						"-6.12773e-19"
					],
					[
						"4426.85",
						"2.58342e-18"
					],
					[
						"4429.50",
						"1.28526e-18"
					],
					[
						"4432.15",
						"1.28575e-18"
					],
					[
						"4434.80",
						"1.91129e-19"
					],
					[
						"4437.45",
						"8.27276e-19"
					],
					[
						"4440.10",
						"8.45137e-19"
					],
					[
						"4442.75",
						"2.23813e-18"
					],
					[
						"4445.40",
						"4.19413e-18"
					],
					[
						"4448.05",
						"2.00311e-18"
					],
					[
						"4450.70",
						"1.72128e-18"
					],
					[
						"4453.35",
						"2.96929e-18"
					],
					[
						"4456.00",
						"1.26784e-18"
					],
					[
						"4458.65",
						"2.04718e-18"
					],
					[
						"4461.30",
						"2.29693e-18"
					],
					[
						"4463.95",
						"1.27083e-18"
					],
					[
						"4466.60",
						"2.55341e-18"
					],
					[
						"4469.25",
						"3.89517e-18"
					],
					[
						"4471.90",
						"1.90043e-18"
					],
					[
						"4474.55",
						"2.56796e-18"
					],
					[
						"4477.20",
						"1.14948e-18"
					],
					[
						"4479.85",
						"1.55636e-18"
					],
					[
						"4482.50",
						"2.27119e-18"
					],
					[
						"4485.15",
						"2.22342e-18"
					],
					[
						"4487.80",
						"2.53524e-18"
					],
					[
						"4490.45",
						"2.18291e-18"
					],
					[
						"4493.10",
						"1.305e-18"
					],
					[
						"4495.75",
						"1.45073e-18"
					],
					[
						"4498.40",
						"1.03393e-18"
					],
					[
						"4501.05",
						"7.64395e-19"
					],
					[
						"4503.70",
						"8.78758e-19"
					],
					[
						"4506.35",
						"2.09951e-18"
					],
					[
						"4509.00",
						"3.65914e-18"
					],
					[
						"4511.65",
						"3.3378e-18"
					],
					[
						"4514.30",
						"2.98791e-18"
					],
					[
						"4516.95",
						"2.40115e-18"
					],
					[
						"4519.60",
						"1.70249e-18"
					],
					[
						"4522.25",
						"4.20239e-18"
					],
					[
						"4524.90",
						"3.17932e-18"
					],
					[
						"4527.55",
						"1.30853e-18"
					],
					[
						"4530.20",
						"2.1423e-18"
					],
					[
						"4532.85",
						"6.86389e-19"
					],
					[
						"4535.50",
						"1.99515e-18"
					],
					[
						"4538.15",
						"2.75418e-18"
					],
					[
						"4540.80",
						"2.61065e-18"
					],
					[
						"4543.45",
						"1.96757e-18"
					],
					[
						"4546.10",
						"2.45991e-18"
					],
					[
						"4548.75",
						"2.49997e-18"
					],
					[
						"4551.40",
						"1.55757e-18"
					],
					[
						"4554.05",
						"1.64183e-18"
					],
					[
						"4556.70",
						"1.99499e-18"
					],
					[
						"4559.35",
						"2.59418e-18"
					],
					[
						"4562.00",
						"2.97899e-18"
					],
					[
						"4564.65",
						"1.09396e-18"
					],
					[
						"4567.30",
						"1.82838e-18"
					],
					[
						"4569.95",
						"2.65376e-18"
					],
					[
						"4572.60",
						"2.18183e-18"
					],
					[
						"4575.25",
						"2.62312e-18"
					],
					[
						"4577.90",
						"1.78066e-18"
					],
					[
						"4580.55",
						"2.53296e-18"
					],
					[
						"4583.20",
						"6.99393e-19"
					],
					[
						"4585.85",
						"1.55835e-18"
					],
					[
						"4588.50",
						"2.61185e-18"
					],
					[
						"4591.15",
						"2.98123e-18"
					],
					[
						"4593.80",
						"1.91416e-18"
					],
					[
						"4596.45",
						"1.52024e-18"
					],
					[
						"4599.10",
						"1.60106e-18"
					],
					[
						"4601.75",
						"1.73549e-18"
					],
					[
						"4604.40",
						"2.19858e-18"
					],
					[
						"4607.05",
						"8.96989e-19"
					],
					[
						"4609.70",
						"2.2519e-18"
					],
					[
						"4612.35",
						"2.78214e-18"
					],
					[
						"4615.00",
						"1.05511e-18"
					],
					[
						"4617.65",
						"1.68466e-18"
					],
					[
						"4620.30",
						"2.37843e-18"
					],
					[
						"4622.95",
						"2.31409e-18"
					],
					[
						"4625.60",
						"1.42213e-18"
					],
					[
						"4628.25",
						"2.36573e-18"
					],
					[
						"4630.90",
						"1.3655e-18"
					],
					[
						"4633.55",
						"1.55636e-18"
					],
					[
						"4636.20",
						"1.9629e-18"
					],
					[
						"4638.85",
						"2.52045e-18"
					],
					[
						"4641.50",
						"1.80238e-18"
					],
					[
						"4644.15",
						"1.65439e-18"
					],
					[
						"4646.80",
						"2.09736e-18"
					],
					[
						"4649.45",
						"2.06387e-18"
					],
					[
						"4652.10",
						"1.78531e-18"
					],
					[
						"4654.75",
						"9.54168e-19"
					],
					[
						"4657.40",
						"1.14102e-18"
					],
					[
						"4660.05",
						"1.87383e-18"
					],
					[
						"4662.70",
						"1.93161e-18"
					],
					[
						"4665.35",
						"1.49459e-18"
					],
					[
						"4668.00",
						"1.64216e-18"
					],
					[
						"4670.65",
						"2.20522e-18"
					],
					[
						"4673.30",
						"2.4544e-18"
					],
					[
						"4675.95",
						"3.38138e-18"
					],
					[
						"4678.60",
						"2.33669e-18"
					],
					[
						"4681.25",
						"1.82283e-18"
					],
					[
						"4683.90",
						"2.14053e-18"
					],
					[
						"4686.55",
						"1.87077e-18"
					],
					[
						"4689.20",
						"8.27804e-19"
					],
					[
						"4691.85",
						"1.74021e-18"
					],
					[
						"4694.50",
						"1.5662e-18"
					],
					[
						"4697.15",
						"1.84228e-18"
					],
					[
						"4699.80",
						"2.14709e-18"
					],
					[
						"4702.45",
						"1.73224e-18"
					],
					[
						"4705.10",
						"2.37621e-18"
					],
					[
						"4707.75",
						"2.15939e-18"
					],
					[
						"4710.40",
						"2.09916e-18"
					],
					[
						"4713.05",
						"2.78095e-18"
					],
					[
						"4715.70",
						"1.95987e-18"
					],
					[
						"4718.35",
						"1.50336e-18"
					],
					[
						"4721.00",
						"2.43329e-18"
					],
					[
						"4723.65",
						"2.06834e-18"
					],
					[
						"4726.30",
						"6.76971e-19"
					],
					[
						"4728.95",
						"1.12461e-18"
					],
					[
						"4731.60",
						"2.738e-18"
					],
					[
						"4734.25",
						"2.63299e-18"
					],
					[
						"4736.90",
						"2.50467e-18"
					],
					[
						"4739.55",
						"1.75626e-18"
					],
					[
						"4742.20",
						"1.79537e-19"
					],
					[
						"4744.85",
						"1.80821e-18"
					],
					[
						"4747.50",
						"6.94688e-19"
					],
					[
						"4750.15",
						"-4.06718e-19"
					],
					[
						"4752.80",
						"1.64492e-18"
					],
					[
						"4755.45",
						"3.05147e-18"
					],
					[
						"4758.10",
						"2.25036e-18"
					],
					[
						"4760.75",
						"1.56044e-18"
					],
					[
						"4763.40",
						"1.28165e-18"
					],
					[
						"4766.05",
						"2.09226e-18"
					],
					[
						"4768.70",
						"2.47993e-18"
					],
					[
						"4771.35",
						"2.09479e-18"
					],
					[
						"4774.00",
						"3.21354e-18"
					],
					[
						"4776.65",
						"2.28778e-18"
					],
					[
						"4779.30",
						"1.2683e-18"
					],
					[
						"4781.95",
						"8.99499e-19"
					],
					[
						"4784.60",
						"1.91577e-18"
					],
					[
						"4787.25",
						"2.57769e-18"
					],
					[
						"4789.90",
						"1.22752e-18"
					],
					[
						"4792.55",
						"1.28772e-18"
					],
					[
						"4795.20",
						"2.58502e-18"
					],
					[
						"4797.85",
						"1.39072e-18"
					],
					[
						"4800.50",
						"4.84678e-19"
					],
					[
						"4803.15",
						"2.50242e-18"
					],
					[
						"4805.80",
						"2.64937e-18"
					],
					[
						"4808.45",
						"2.37425e-18"
					],
					[
						"4811.10",
						"2.41531e-18"
					],
					[
						"4813.75",
						"2.10039e-18"
					],
					[
						"4816.40",
						"1.87595e-18"
					],
					[
						"4819.05",
						"2.39983e-18"
					],
					[
						"4821.70",
						"2.9461e-18"
					],
					[
						"4824.35",
						"1.78022e-18"
					],
					[
						"4827.00",
						"1.20907e-18"
					],
					[
						"4829.65",
						"1.9616e-18"
					],
					[
						"4832.30",
						"2.23928e-18"
					],
					[
						"4834.95",
						"2.12647e-18"
					],
					[
						"4837.60",
						"1.03809e-18"
					],
					[
						"4840.25",
						"2.45056e-18"
					],
					[
						"4842.90",
						"2.035e-18"
					],
					[
						"4845.55",
						"1.126e-18"
					],
					[
						"4848.20",
						"1.46467e-18"
					],
					[
						"4850.85",
						"2.39728e-18"
					],
					[
						"4853.50",
						"2.36758e-18"
					],
					[
						"4856.15",
						"2.48615e-18"
					],
					[
						"4858.80",
						"1.75532e-18"
					],
					[
						"4861.45",
						"1.71668e-18"
					],
					[
						"4864.10",
						"1.90884e-18"
					],
					[
						"4866.75",
						"2.83033e-18"
					],
					[
						"4869.40",
						"9.91169e-19"
					],
					[
						"4872.05",
						"1.04485e-18"
					],
					[
						"4874.70",
						"1.9536e-18"
					],
					[
						"4877.35",
						"3.23259e-18"
					],
					[
						"4880.00",
						"2.49102e-18"
					],
					[
						"4882.65",
						"2.71261e-18"
					],
					[
						"4885.30",
						"3.36949e-18"
					],
					[
						"4887.95",
						"1.90012e-18"
					],
					[
						"4890.60",
						"1.82574e-18"
					],
					[
						"4893.25",
						"1.60097e-18"
					],
					[
						"4895.90",
						"2.02083e-18"
					],
					[
						"4898.55",
						"2.22042e-18"
					],
					[
						"4901.20",
						"1.53971e-18"
					],
					[
						"4903.85",
						"8.59138e-19"
					],
					[
						"4906.50",
						"9.28805e-19"
					],
					[
						"4909.15",
						"2.48707e-18"
					],
					[
						"4911.80",
						"1.80361e-18"
					],
					[
						"4914.45",
						"1.6137e-18"
					],
					[
						"4917.10",
						"2.23919e-18"
					],
					[
						"4919.75",
						"1.69393e-18"
					],
					[
						"4922.40",
						"2.2917e-18"
					],
					[
						"4925.05",
						"3.91359e-18"
					],
					[
						"4927.70",
						"2.94657e-18"
					],
					[
						"4930.35",
						"1.72915e-18"
					],
					[
						"4933.00",
						"1.61134e-18"
					],
					[
						"4935.65",
						"1.63112e-18"
					],
					[
						"4938.30",
						"2.60154e-18"
					],
					[
						"4940.95",
						"2.72145e-18"
					],
					[
						"4943.60",
						"2.00094e-18"
					],
					[
						"4946.25",
						"1.63615e-18"
					],
					[
						"4948.90",
						"1.43926e-18"
					],
					[
						"4951.55",
						"1.63116e-18"
					],
					[
						"4954.20",
						"1.78445e-18"
					],
					[
						"4956.85",
						"2.66886e-18"
					],
					[
						"4959.50",
						"1.64087e-18"
					],
					[
						"4962.15",
						"1.29469e-18"
					],
					[
						"4964.80",
						"2.30598e-18"
					],
					[
						"4967.45",
						"2.73889e-18"
					],
					[
						"4970.10",
						"2.2232e-18"
					],
					[
						"4972.75",
						"1.30976e-18"
					],
					[
						"4975.40",
						"1.49217e-18"
					],
					[
						"4978.05",
						"1.7295e-18"
					],
					[
						"4980.70",
						"1.82156e-18"
					],
					[
						"4983.35",
						"1.8885e-18"
					],
					[
						"4986.00",
						"1.48622e-18"
					],
					[
						"4988.65",
						"1.96629e-18"
					],
					[
						"4991.30",
						"1.42235e-18"
					],
					[
						"4993.95",
						"1.97937e-18"
					],
					[
						"4996.60",
						"2.15905e-18"
					],
					[
						"4999.25",
						"2.61476e-18"
					],
					[
						"5001.90",
						"2.20826e-18"
					],
					[
						"5004.55",
						"1.81718e-18"
					],
					[
						"5007.20",
						"3.06789e-18"
					],
					[
						"5009.85",
						"1.73974e-18"
					],
					[
						"5012.50",
						"1.61279e-18"
					],
					[
						"5015.15",
						"2.30044e-18"
					],
					[
						"5017.80",
						"2.10988e-18"
					],
					[
						"5020.45",
						"1.23463e-18"
					],
					[
						"5023.10",
						"7.76519e-19"
					],
					[
						"5025.75",
						"1.35313e-18"
					],
					[
						"5028.40",
						"1.61091e-18"
					],
					[
						"5031.05",
						"1.1098e-18"
					],
					[
						"5033.70",
						"1.12455e-18"
					],
					[
						"5036.35",
						"1.14629e-18"
					],
					[
						"5039.00",
						"1.20788e-18"
					],
					[
						"5041.65",
						"1.68359e-18"
					],
					[
						"5044.30",
						"1.85566e-18"
					],
					[
						"5046.95",
						"1.18041e-18"
					],
					[
						"5049.60",
						"1.53329e-18"
					],
					[
						"5052.25",
						"2.74848e-18"
					],
					[
						"5054.90",
						"1.5723e-18"
					],
					[
						"5057.55",
						"1.24194e-18"
					],
					[
						"5060.20",
						"3.03902e-18"
					],
					[
						"5062.85",
						"1.28762e-18"
					],
					[
						"5065.50",
						"6.94833e-19"
					],
					[
						"5068.15",
						"1.42557e-18"
					],
					[
						"5070.80",
						"1.85324e-18"
					],
					[
						"5073.45",
						"2.7444e-18"
					],
					[
						"5076.10",
						"1.65321e-18"
					],
					[
						"5078.75",
						"2.06074e-18"
					],
					[
						"5081.40",
						"2.59362e-18"
					],
					[
						"5084.05",
						"2.25187e-18"
					],
					[
						"5086.70",
						"1.71492e-18"
					],
					[
						"5089.35",
						"1.01346e-18"
					],
					[
						"5092.00",
						"1.91734e-18"
					],
					[
						"5094.65",
						"2.72275e-18"
					],
					[
						"5097.30",
						"1.86333e-18"
					],
					[
						"5099.95",
						"1.74666e-18"
					],
					[
						"5102.60",
						"1.82509e-18"
					],
					[
						"5105.25",
						"2.78111e-18"
					],
					[
						"5107.90",
						"2.0446e-18"
					],
					[
						"5110.55",
						"1.54547e-18"
					],
					[
						"5113.20",
						"1.1526e-18"
					],
					[
						"5115.85",
						"9.04446e-19"
					],
					[
						"5118.50",
						"1.78872e-18"
					],
					[
						"5121.15",
						"1.71851e-18"
					],
					[
						"5123.80",
						"1.62838e-18"
					],
					[
						"5126.45",
						"1.98177e-18"
					],
					[
						"5129.10",
						"1.52451e-18"
					],
					[
						"5131.75",
						"1.77609e-18"
					],
					[
						"5134.40",
						"1.82513e-18"
					],
					[
						"5137.05",
						"2.19392e-18"
					],
					[
						"5139.70",
						"2.23671e-18"
					],
					[
						"5142.35",
						"1.92147e-18"
					],
					[
						"5145.00",
						"2.10913e-18"
					],
					[
						"5147.65",
						"1.97984e-18"
					],
					[
						"5150.30",
						"2.00631e-18"
					],
					[
						"5152.95",
						"2.23792e-18"
					],
					[
						"5155.60",
						"1.60159e-18"
					],
					[
						"5158.25",
						"1.24707e-18"
					],
					[
						"5160.90",
						"1.65783e-18"
					],
					[
						"5163.55",
						"1.44372e-18"
					],
					[
						"5166.20",
						"1.67605e-18"
					],
					[
						"5168.85",
						"1.69908e-18"
					],
					[
						"5171.50",
						"1.8026e-18"
					],
					[
						"5174.15",
						"2.41357e-18"
					],
					[
						"5176.80",
						"1.52699e-18"
					],
					[
						"5179.45",
						"1.3723e-18"
					],
					[
						"5182.10",
						"1.96494e-18"
					],
					[
						"5184.75",
						"1.48614e-18"
					],
					[
						"5187.40",
						"1.9046e-18"
					],
					[
						"5190.05",
						"2.16218e-18"
					],
					[
						"5192.70",
						"1.20792e-18"
					],
					[
						"5195.35",
						"1.25332e-18"
					],
					[
						"5198.00",
						"1.56823e-18"
					],
					[
						"5200.65",
						"1.95291e-18"
					],
					[
						"5203.30",
						"2.54691e-18"
					],
					[
						"5205.95",
						"2.13192e-18"
					],
					[
						"5208.60",
						"2.19939e-18"
					],
					[
						"5211.25",
						"1.74232e-18"
					],
					[
						"5213.90",
						"1.66864e-18"
					],
					[
						"5216.55",
						"1.54737e-18"
					],
					[
						"5219.20",
						"1.21968e-18"
					],
					[
						"5221.85",
						"2.36922e-18"
					],
					[
						"5224.50",
						"2.80249e-18"
					],
					[
						"5227.15",
						"2.0659e-18"
					],
					[
						"5229.80",
						"8.00986e-19"
					],
					[
						"5232.45",
						"1.36356e-18"
					],
					[
						"5235.10",
						"1.98482e-18"
					],
					[
						"5237.75",
						"1.37103e-18"
					],
					[
						"5240.40",
						"1.52102e-18"
					],
					[
						"5243.05",
						"1.62462e-18"
					],
					[
						"5245.70",
						"1.31389e-18"
					],
					[
						"5248.35",
						"2.41629e-18"
					],
					[
						"5251.00",
						"2.30351e-18"
					],
					[
						"5253.65",
						"1.71855e-18"
					],
					[
						"5256.30",
						"2.12687e-18"
					],
					[
						"5258.95",
						"2.16484e-18"
					],
					[
						"5261.60",
						"2.53017e-18"
					],
					[
						"5264.25",
						"2.23933e-18"
					],
					[
						"5266.90",
						"2.15634e-18"
					],
					[
						"5269.55",
						"2.62041e-18"
					],
					[
						"5272.20",
						"1.4964e-18"
					],
					[
						"5274.85",
						"1.81226e-18"
					],
					[
						"5277.50",
						"2.09892e-18"
					],
					[
						"5280.15",
						"1.64449e-18"
					],
					[
						"5282.80",
						"2.27123e-18"
					],
					[
						"5285.45",
						"1.1135e-18"
					],
					[
						"5288.10",
						"1.20085e-18"
					],
					[
						"5290.75",
						"2.44965e-18"
					],
					[
						"5293.40",
						"2.41755e-18"
					],
					[
						"5296.05",
						"1.3438e-18"
					],
					[
						"5298.70",
						"7.62282e-19"
					],
					[
						"5301.35",
						"1.25947e-18"
					],
					[
						"5304.00",
						"1.54951e-18"
					],
					[
						"5306.65",
						"1.51494e-18"
					],
					[
						"5309.30",
						"2.02309e-18"
					],
					[
						"5311.95",
						"1.94133e-18"
					],
					[
						"5314.60",
						"1.74542e-18"
					],
					[
						"5317.25",
						"1.60983e-18"
					],
					[
						"5319.90",
						"1.27838e-18"
					],
					[
						"5322.55",
						"1.64711e-18"
					],
					[
						"5325.20",
						"1.34378e-18"
					],
					[
						"5327.85",
						"2.10304e-18"
					],
					[
						"5330.50",
						"2.38443e-18"
					],
					[
						"5333.15",
						"1.85532e-18"
					],
					[
						"5335.80",
						"1.23212e-18"
					],
					[
						"5338.45",
						"2.02779e-18"
					],
					[
						"5341.10",
						"2.27639e-18"
					],
					[
						"5343.75",
						"1.75498e-18"
					],
					[
						"5346.40",
						"1.92302e-18"
					],
					[
						"5349.05",
						"2.11361e-18"
					],
					[
						"5351.70",
						"2.501e-18"
					],
					[
						"5354.35",
						"2.34188e-18"
					],
					[
						"5357.00",
						"1.38062e-18"
					],
					[
						"5359.65",
						"5.92512e-19"
					],
					[
						"5362.30",
						"1.32988e-18"
					],
					[
						"5364.95",
						"1.77845e-18"
					],
					[
						"5367.60",
						"9.44773e-19"
					],
					[
						"5370.25",
						"1.75407e-18"
					],
					[
						"5372.90",
						"2.33431e-18"
					],
					[
						"5375.55",
						"1.73205e-18"
					],
					[
						"5378.20",
						"1.70191e-18"
					],
					[
						"5380.85",
						"1.3098e-18"
					],
					[
						"5383.50",
						"2.44809e-18"
					],
					[
						"5386.15",
						"2.23511e-18"
					],
					[
						"5388.80",
						"2.46023e-18"
					],
					[
						"5391.45",
						"2.84024e-18"
					],
					[
						"5394.10",
						"1.84919e-18"
					],
					[
						"5396.75",
						"2.02272e-18"
					],
					[
						"5399.40",
						"2.06156e-18"
					],
					[
						"5402.05",
						"1.22284e-18"
					],
					[
						"5404.70",
						"1.58194e-18"
					],
					[
						"5407.35",
						"2.62054e-18"
					],
					[
						"5410.00",
						"2.60188e-18"
					],
					[
						"5412.65",
						"1.48104e-18"
					],
					[
						"5415.30",
						"7.65032e-19"
					],
					[
						"5417.95",
						"1.31674e-18"
					],
					[
						"5420.60",
						"9.36079e-19"
					],
					[
						"5423.25",
						"1.16394e-18"
					],
					[
						"5425.90",
						"1.5577e-18"
					],
					[
						"5428.55",
						"1.60171e-18"
					],
					[
						"5431.20",
						"1.83454e-18"
					],
					[
						"5433.85",
						"2.00896e-18"
					],
					[
						"5436.50",
						"2.45587e-18"
					],
					[
						"5439.15",
						"1.22591e-18"
					],
					[
						"5441.80",
						"1.56943e-18"
					],
					[
						"5444.45",
						"2.17789e-18"
					],
					[
						"5447.10",
						"8.37009e-19"
					],
					[
						"5449.75",
						"1.19919e-19"
					],
					[
						"5452.40",
						"1.38613e-18"
					],
					[
						"5455.05",
						"1.92166e-18"
					],
					[
						"5457.70",
						"2.76633e-18"
					],
					[
						"5460.35",
						"2.04227e-18"
					],
					[
						"5463.00",
						"1.48683e-18"
					],
					[
						"5465.65",
						"2.28463e-18"
					],
					[
						"5468.30",
						"6.01189e-19"
					],
					[
						"5470.95",
						"3.77207e-19"
					],
					[
						"5473.60",
						"1.11755e-18"
					],
					[
						"5476.25",
						"1.77209e-18"
					],
					[
						"5478.90",
						"1.46145e-18"
					],
					[
						"5481.55",
						"1.16204e-18"
					],
					[
						"5484.20",
						"1.27707e-18"
					],
					[
						"5486.85",
						"7.65595e-19"
					],
					[
						"5489.50",
						"6.41904e-19"
					],
					[
						"5492.15",
						"2.0681e-18"
					],
					[
						"5494.80",
						"2.02923e-18"
					],
					[
						"5497.45",
						"1.27086e-18"
					],
					[
						"5500.10",
						"1.53723e-18"
					],
					[
						"5502.75",
						"1.50932e-18"
					],
					[
						"5505.40",
						"1.46362e-18"
					],
					[
						"5508.05",
						"9.1447e-19"
					],
					[
						"5510.70",
						"3.7504e-19"
					],
					[
						"5513.35",
						"1.4452e-18"
					],
					[
						"5516.00",
						"2.49188e-18"
					],
					[
						"5518.65",
						"2.29171e-18"
					],
					[
						"5521.30",
						"1.73889e-18"
					],
					[
						"5523.95",
						"1.147e-18"
					],
					[
						"5526.60",
						"1.695e-18"
					],
					[
						"5529.25",
						"1.97357e-18"
					],
					[
						"5531.90",
						"1.66728e-18"
					],
					[
						"5534.55",
						"1.94129e-18"
					],
					[
						"5537.20",
						"1.66978e-18"
					],
					[
						"5539.85",
						"1.3877e-18"
					],
					[
						"5542.50",
						"8.11506e-19"
					],
					[
						"5545.15",
						"9.1073e-19"
					],
					[
						"5547.80",
						"1.62807e-18"
					],
					[
						"5550.45",
						"9.92784e-19"
					],
					[
						"5553.10",
						"1.08238e-18"
					],
					[
						"5555.75",
						"1.5084e-18"
					],
					[
						"5558.40",
						"1.20486e-18"
					],
					[
						"5561.05",
						"1.48814e-18"
					],
					[
						"5563.70",
						"1.77142e-18"
					],
					[
						"5566.35",
						"2.0547e-18"
					],
					[
						"5569.00",
						"2.33798e-18"
					],
					[
						"5571.65",
						"2.62126e-18"
					],
					[
						"5574.30",
						"2.90454e-18"
					],
					[
						"5576.95",
						"3.18782e-18"
					],
					[
						"5579.60",
						"3.4711e-18"
					],
					[
						"5582.25",
						"3.4711e-18"
					],
					[
						"5584.90",
						"3.44935e-18"
					],
					[
						"5587.55",
						"4.98041e-18"
					],
					[
						"5590.20",
						"6.66992e-18"
					],
					[
						"5592.85",
						"6.28811e-18"
					],
					[
						"5595.50",
						"4.70833e-18"
					],
					[
						"5598.15",
						"3.76474e-18"
					],
					[
						"5600.80",
						"2.27476e-18"
					],
					[
						"5603.45",
						"3.25685e-19"
					],
					[
						"5606.10",
						"1.20532e-18"
					],
					[
						"5608.75",
						"1.64805e-18"
					],
					[
						"5611.40",
						"1.72643e-18"
					],
					[
						"5614.05",
						"1.50918e-18"
					],
					[
						"5616.70",
						"1.47911e-18"
					],
					[
						"5619.35",
						"2.55535e-18"
					],
					[
						"5622.00",
						"2.15426e-18"
					],
					[
						"5624.65",
						"1.16264e-18"
					],
					[
						"5627.30",
						"1.66102e-18"
					],
					[
						"5629.95",
						"1.69263e-18"
					],
					[
						"5632.60",
						"1.06548e-18"
					],
					[
						"5635.25",
						"8.86291e-19"
					],
					[
						"5637.90",
						"1.88824e-18"
					],
					[
						"5640.55",
						"1.46166e-18"
					],
					[
						"5643.20",
						"1.47167e-18"
					],
					[
						"5645.85",
						"1.75983e-18"
					],
					[
						"5648.50",
						"1.20512e-18"
					],
					[
						"5651.15",
						"7.33377e-19"
					],
					[
						"5653.80",
						"1.75824e-18"
					],
					[
						"5656.45",
						"1.61027e-18"
					],
					[
						"5659.10",
						"1.14762e-18"
					],
					[
						"5661.75",
						"5.54683e-19"
					],
					[
						"5664.40",
						"1.55674e-18"
					],
					[
						"5667.05",
						"1.5946e-18"
					],
					[
						"5669.70",
						"1.93796e-18"
					],
					[
						"5672.35",
						"2.06585e-18"
					],
					[
						"5675.00",
						"9.79778e-19"
					],
					[
						"5677.65",
						"1.28073e-18"
					],
					[
						"5680.30",
						"2.05053e-18"
					],
					[
						"5682.95",
						"1.87416e-18"
					],
					[
						"5685.60",
						"1.73551e-18"
					],
					[
						"5688.25",
						"1.45375e-18"
					],
					[
						"5690.90",
						"1.0944e-18"
					],
					[
						"5693.55",
						"1.00812e-18"
					],
					[
						"5696.20",
						"1.65168e-18"
					],
					[
						"5698.85",
						"1.62392e-18"
					],
					[
						"5701.50",
						"2.41061e-18"
					],
					[
						"5704.15",
						"2.18119e-18"
					],
					[
						"5706.80",
						"1.7093e-18"
					],
					[
						"5709.45",
						"1.48536e-18"
					],
					[
						"5712.10",
						"1.65913e-18"
					],
					[
						"5714.75",
						"1.33477e-18"
					],
					[
						"5717.40",
						"1.6163e-18"
					],
					[
						"5720.05",
						"2.45361e-18"
					],
					[
						"5722.70",
						"2.46718e-18"
					],
					[
						"5725.35",
						"2.37221e-18"
					],
					[
						"5728.00",
						"2.36559e-18"
					],
					[
						"5730.65",
						"1.4679e-18"
					],
					[
						"5733.30",
						"1.44017e-18"
					],
					[
						"5735.95",
						"1.8134e-18"
					],
					[
						"5738.60",
						"2.04605e-18"
					],
					[
						"5741.25",
						"1.42091e-18"
					],
					[
						"5743.90",
						"1.58206e-18"
					],
					[
						"5746.55",
						"1.70354e-18"
					],
					[
						"5749.20",
						"1.30503e-18"
					],
					[
						"5751.85",
						"1.64061e-18"
					],
					[
						"5754.50",
						"7.60678e-19"
					],
					[
						"5757.15",
						"7.75547e-19"
					],
					[
						"5759.80",
						"7.99228e-19"
					],
					[
						"5762.45",
						"1.38386e-18"
					],
					[
						"5765.10",
						"2.40539e-18"
					],
					[
						"5767.75",
						"2.20905e-18"
					],
					[
						"5770.40",
						"2.25403e-18"
					],
					[
						"5773.05",
						"2.44959e-18"
					],
					[
						"5775.70",
						"2.19614e-18"
					],
					[
						"5778.35",
						"1.4922e-18"
					],
					[
						"5781.00",
						"1.89915e-18"
					],
					[
						"5783.65",
						"1.91043e-18"
					],
					[
						"5786.30",
						"2.27486e-18"
					],
					[
						"5788.95",
						"3.20897e-18"
					],
					[
						"5791.60",
						"2.30243e-18"
					],
					[
						"5794.25",
						"1.76257e-18"
					],
					[
						"5796.90",
						"2.31118e-18"
					],
					[
						"5799.55",
						"2.08329e-18"
					],
					[
						"5802.20",
						"2.87567e-18"
					],
					[
						"5804.85",
						"2.67421e-18"
					],
					[
						"5807.50",
						"2.12036e-18"
					],
					[
						"5810.15",
						"1.29526e-18"
					],
					[
						"5812.80",
						"1.44558e-18"
					],
					[
						"5815.45",
						"2.32648e-18"
					],
					[
						"5818.10",
						"1.77083e-18"
					],
					[
						"5820.75",
						"2.25179e-18"
					],
					[
						"5823.40",
						"2.33502e-18"
					],
					[
						"5826.05",
						"1.44572e-18"
					],
					[
						"5828.70",
						"1.04916e-18"
					],
					[
						"5831.35",
						"1.66738e-18"
					],
					[
						"5834.00",
						"2.33045e-18"
					],
					[
						"5836.65",
						"1.70413e-18"
					],
					[
						"5839.30",
						"6.25279e-19"
					],
					[
						"5841.95",
						"1.24858e-18"
					],
					[
						"5844.60",
						"1.7779e-18"
					],
					[
						"5847.25",
						"1.48577e-18"
					],
					[
						"5849.90",
						"1.5967e-18"
					],
					[
						"5852.55",
						"1.70818e-18"
					],
					[
						"5855.20",
						"2.36104e-18"
					],
					[
						"5857.85",
						"1.85615e-18"
					],
					[
						"5860.50",
						"1.62e-18"
					],
					[
						"5863.15",
						"2.67091e-18"
					],
					[
						"5865.80",
						"2.46151e-18"
					],
					[
						"5868.45",
						"1.57476e-18"
					],
					[
						"5871.10",
						"2.40705e-18"
					],
					[
						"5873.75",
						"2.97791e-18"
					],
					[
						"5876.40",
						"2.95545e-18"
					],
					[
						"5879.05",
						"2.65001e-18"
					],
					[
						"5881.70",
						"2.17754e-18"
					],
					[
						"5884.35",
						"1.13122e-18"
					],
					[
						"5887.00",
						"-5.36113e-19"
					],
					[
						"5889.65",
						"-3.52942e-20"
					],
					[
						"5892.30",
						"8.8183e-19"
					],
					[
						"5894.95",
						"2.45715e-18"
					],
					[
						"5897.60",
						"2.74368e-18"
					],
					[
						"5900.25",
						"1.50382e-18"
					],
					[
						"5902.90",
						"1.65024e-18"
					],
					[
						"5905.55",
						"2.05603e-18"
					],
					[
						"5908.20",
						"3.02651e-18"
					],
					[
						"5910.85",
						"2.29633e-18"
					],
					[
						"5913.50",
						"1.35143e-18"
					],
					[
						"5916.15",
						"2.58326e-18"
					],
					[
						"5918.80",
						"3.16265e-18"
					],
					[
						"5921.45",
						"1.64479e-18"
					],
					[
						"5924.10",
						"1.07253e-18"
					],
					[
						"5926.75",
						"1.52448e-18"
					],
					[
						"5929.40",
						"2.28022e-18"
					],
					[
						"5932.05",
						"2.30382e-18"
					],
					[
						"5934.70",
						"2.16468e-18"
					],
					[
						"5937.35",
						"1.72171e-18"
					],
					[
						"5940.00",
						"1.43123e-18"
					],
					[
						"5942.65",
						"1.16016e-18"
					],
					[
						"5945.30",
						"1.58711e-18"
					],
					[
						"5947.95",
						"1.93976e-18"
					],
					[
						"5950.60",
						"1.66189e-18"
					],
					[
						"5953.25",
						"1.31189e-18"
					],
					[
						"5955.90",
						"1.06098e-18"
					],
					[
						"5958.55",
						"1.82797e-18"
					],
					[
						"5961.20",
						"1.77901e-18"
					],
					[
						"5963.85",
						"2.21064e-18"
					],
					[
						"5966.50",
						"2.59833e-18"
					],
					[
						"5969.15",
						"2.99827e-18"
					],
					[
						"5971.80",
						"2.68736e-18"
					],
					[
						"5974.45",
						"2.0767e-18"
					],
					[
						"5977.10",
						"1.57207e-18"
					],
					[
						"5979.75",
						"1.31112e-18"
					],
					[
						"5982.40",
						"1.63959e-18"
					],
					[
						"5985.05",
						"2.05963e-18"
					],
					[
						"5987.70",
						"1.96539e-18"
					],
					[
						"5990.35",
						"1.76645e-18"
					],
					[
						"5993.00",
						"2.0551e-18"
					],
					[
						"5995.65",
						"2.60386e-18"
					],
					[
						"5998.30",
						"2.32535e-18"
					],
					[
						"6000.95",
						"1.91576e-18"
					],
					[
						"6003.60",
						"2.43376e-18"
					],
					[
						"6006.25",
						"1.90265e-18"
					],
					[
						"6008.90",
						"2.11272e-18"
					],
					[
						"6011.55",
						"2.12998e-18"
					],
					[
						"6014.20",
						"1.86133e-18"
					],
					[
						"6016.85",
						"2.05967e-18"
					],
					[
						"6019.50",
						"1.87313e-18"
					],
					[
						"6022.15",
						"1.55333e-18"
					],
					[
						"6024.80",
						"2.28054e-18"
					],
					[
						"6027.45",
						"2.89237e-18"
					],
					[
						"6030.10",
						"2.15466e-18"
					],
					[
						"6032.75",
						"1.76164e-18"
					],
					[
						"6035.40",
						"2.01855e-18"
					],
					[
						"6038.05",
						"2.78501e-18"
					],
					[
						"6040.70",
						"2.8894e-18"
					],
					[
						"6043.35",
						"2.56333e-18"
					],
					[
						"6046.00",
						"2.39725e-18"
					],
					[
						"6048.65",
						"1.78127e-18"
					],
					[
						"6051.30",
						"2.17296e-18"
					],
					[
						"6053.95",
						"1.98581e-18"
					],
					[
						"6056.60",
						"1.75168e-18"
					],
					[
						"6059.25",
						"1.7721e-18"
					],
					[
						"6061.90",
						"1.32062e-18"
					],
					[
						"6064.55",
						"1.09391e-18"
					],
					[
						"6067.20",
						"1.75883e-18"
					],
					[
						"6069.85",
						"2.72163e-18"
					],
					[
						"6072.50",
						"2.7782e-18"
					],
					[
						"6075.15",
						"2.40569e-18"
					],
					[
						"6077.80",
						"1.81646e-18"
					],
					[
						"6080.45",
						"1.92157e-18"
					],
					[
						"6083.10",
						"2.47565e-18"
					],
					[
						"6085.75",
						"2.47848e-18"
					],
					[
						"6088.40",
						"2.11427e-18"
					],
					[
						"6091.05",
						"1.54047e-18"
					],
					[
						"6093.70",
						"2.02633e-18"
					],
					[
						"6096.35",
						"2.38893e-18"
					],
					[
						"6099.00",
						"2.59727e-18"
					],
					[
						"6101.65",
						"1.85122e-18"
					],
					[
						"6104.30",
						"1.3186e-18"
					],
					[
						"6106.95",
						"2.07887e-18"
					],
					[
						"6109.60",
						"2.24299e-18"
					],
					[
						"6112.25",
						"1.4307e-18"
					],
					[
						"6114.90",
						"2.43934e-18"
					],
					[
						"6117.55",
						"2.63871e-18"
					],
					[
						"6120.20",
						"2.32568e-18"
					],
					[
						"6122.85",
						"2.13987e-18"
					],
					[
						"6125.50",
						"1.84937e-18"
					],
					[
						"6128.15",
						"2.26253e-18"
					],
					[
						"6130.80",
						"2.11657e-18"
					],
					[
						"6133.45",
						"1.30719e-18"
					],
					[
						"6136.10",
						"1.95111e-18"
					],
					[
						"6138.75",
						"2.16477e-18"
					],
					[
						"6141.40",
						"1.46461e-18"
					],
					[
						"6144.05",
						"1.61804e-18"
					],
					[
						"6146.70",
						"1.73572e-18"
					],
					[
						"6149.35",
						"6.22874e-19"
					],
					[
						"6152.00",
						"4.58737e-19"
					],
					[
						"6154.65",
						"1.46969e-18"
					],
					[
						"6157.30",
						"1.52668e-18"
					],
					[
						"6159.95",
						"1.94134e-18"
					],
					[
						"6162.60",
						"2.74178e-18"
					],
					[
						"6165.25",
						"2.51074e-18"
					],
					[
						"6167.90",
						"2.5192e-18"
					],
					[
						"6170.55",
						"2.64249e-18"
					],
					[
						"6173.20",
						"2.52299e-18"
					],
					[
						"6175.85",
						"2.43202e-18"
					],
					[
						"6178.50",
						"1.76356e-18"
					],
					[
						"6181.15",
						"2.00957e-18"
					],
					[
						"6183.80",
						"2.88753e-18"
					],
					[
						"6186.45",
						"2.16437e-18"
					],
					[
						"6189.10",
						"1.84435e-18"
					],
					[
						"6191.75",
						"1.73255e-18"
					],
					[
						"6194.40",
						"1.31757e-18"
					],
					[
						"6197.05",
						"1.63133e-18"
					],
					[
						"6199.70",
						"2.18958e-18"
					],
					[
						"6202.35",
						"1.92576e-18"
					],
					[
						"6205.00",
						"1.94484e-18"
					],
					[
						"6207.65",
						"2.4254e-18"
					],
					[
						"6210.30",
						"2.10832e-18"
					],
					[
						"6212.95",
						"2.26204e-18"
					],
					[
						"6215.60",
						"1.53608e-18"
					],
					[
						"6218.25",
						"1.04118e-18"
					],
					[
						"6220.90",
						"2.22972e-18"
					],
					[
						"6223.55",
						"2.4981e-18"
					],
					[
						"6226.20",
						"1.60269e-18"
					],
					[
						"6228.85",
						"1.62088e-18"
					],
					[
						"6231.50",
						"1.93706e-18"
					],
					[
						"6234.15",
						"1.99744e-18"
					],
					[
						"6236.80",
						"2.15041e-18"
					],
					[
						"6239.45",
						"2.81041e-18"
					],
					[
						"6242.10",
						"2.24606e-18"
					],
					[
						"6244.75",
						"1.419e-18"
					],
					[
						"6247.40",
						"1.8501e-18"
					],
					[
						"6250.05",
						"1.76881e-18"
					],
					[
						"6252.70",
						"1.85055e-18"
					],
					[
						"6255.35",
						"1.81898e-18"
					],
					[
						"6258.00",
						"1.9269e-18"
					],
					[
						"6260.65",
						"2.50371e-18"
					],
					[
						"6263.30",
						"2.12665e-18"
					],
					[
						"6265.95",
						"1.62176e-18"
					],
					[
						"6268.60",
						"1.9603e-18"
					],
					[
						"6271.25",
						"2.74641e-18"
					],
					[
						"6273.90",
						"1.58408e-18"
					],
					[
						"6276.55",
						"1.06931e-18"
					],
					[
						"6279.20",
						"1.33081e-18"
					],
					[
						"6281.85",
						"1.20654e-18"
					],
					[
						"6284.50",
						"1.54737e-18"
					],
					[
						"6287.15",
						"4.64612e-19"
					],
					[
						"6289.80",
						"-9.97581e-20"
					],
					[
						"6292.45",
						"1.72449e-18"
					],
					[
						"6295.10",
						"2.94247e-18"
					],
					[
						"6297.75",
						"2.70267e-18"
					],
					[
						"6300.40",
						"1.06521e-18"
					],
					[
						"6303.05",
						"8.25101e-19"
					],
					[
						"6305.70",
						"8.55659e-19"
					],
					[
						"6308.35",
						"5.34767e-19"
					],
					[
						"6311.00",
						"1.45475e-18"
					],
					[
						"6313.65",
						"1.48365e-18"
					],
					[
						"6316.30",
						"1.54046e-18"
					],
					[
						"6318.95",
						"1.51105e-18"
					],
					[
						"6321.60",
						"1.25957e-18"
					],
					[
						"6324.25",
						"1.39316e-18"
					],
					[
						"6326.90",
						"1.71396e-18"
					],
					[
						"6329.55",
						"1.88248e-18"
					],
					[
						"6332.20",
						"1.38274e-18"
					],
					[
						"6334.85",
						"1.35009e-18"
					],
					[
						"6337.50",
						"2.38619e-18"
					],
					[
						"6340.15",
						"2.32954e-18"
					],
					[
						"6342.80",
						"1.58186e-18"
					],
					[
						"6345.45",
						"1.93454e-18"
					],
					[
						"6348.10",
						"2.33277e-18"
					],
					[
						"6350.75",
						"1.96309e-18"
					],
					[
						"6353.40",
						"2.1271e-18"
					],
					[
						"6356.05",
						"2.45026e-18"
					],
					[
						"6358.70",
						"2.13223e-18"
					],
					[
						"6361.35",
						"1.93914e-18"
					],
					[
						"6364.00",
						"2.33509e-18"
					],
					[
						"6366.65",
						"2.71867e-18"
					],
					[
						"6369.30",
						"1.67421e-18"
					],
					[
						"6371.95",
						"1.07469e-18"
					],
					[
						"6374.60",
						"1.20577e-18"
					],
					[
						"6377.25",
						"2.11451e-18"
					],
					[
						"6379.90",
						"1.7383e-18"
					],
					[
						"6382.55",
						"1.25035e-18"
					],
					[
						"6385.20",
						"1.7598e-18"
					],
					[
						"6387.85",
						"1.26223e-18"
					],
					[
						"6390.50",
						"1.11013e-18"
					],
					[
						"6393.15",
						"1.10331e-18"
					],
					[
						"6395.80",
						"1.64337e-18"
					],
					[
						"6398.45",
						"2.12892e-18"
					],
					[
						"6401.10",
						"1.86886e-18"
					],
					[
						"6403.75",
						"1.48492e-18"
					],
					[
						"6406.40",
						"1.57954e-18"
					],
					[
						"6409.05",
						"1.97321e-18"
					],
					[
						"6411.70",
						"1.60355e-18"
					],
					[
						"6414.35",
						"2.14844e-18"
					],
					[
						"6417.00",
						"2.26218e-18"
					],
					[
						"6419.65",
						"1.9194e-18"
					],
					[
						"6422.30",
						"1.80148e-18"
					],
					[
						"6424.95",
						"1.92078e-18"
					],
					[
						"6427.60",
						"2.40372e-18"
					],
					[
						"6430.25",
						"1.67884e-18"
					],
					[
						"6432.90",
						"9.58355e-19"
					],
					[
						"6435.55",
						"1.46646e-18"
					],
					[
						"6438.20",
						"1.85958e-18"
					],
					[
						"6440.85",
						"1.86751e-18"
					],
					[
						"6443.50",
						"1.63582e-18"
					],
					[
						"6446.15",
						"2.14699e-18"
					],
					[
						"6448.80",
						"2.39964e-18"
					],
					[
						"6451.45",
						"2.45849e-18"
					],
					[
						"6454.10",
						"8.16925e-19"
					],
					[
						"6456.75",
						"1.99922e-19"
					],
					[
						"6459.40",
						"1.92441e-18"
					],
					[
						"6462.05",
						"2.45108e-18"
					],
					[
						"6464.70",
						"1.81554e-18"
					],
					[
						"6467.35",
						"2.05856e-18"
					],
					[
						"6470.00",
						"2.29829e-18"
					],
					[
						"6472.65",
						"1.82495e-18"
					],
					[
						"6475.30",
						"2.32713e-18"
					],
					[
						"6477.95",
						"1.83594e-18"
					],
					[
						"6480.60",
						"1.15669e-18"
					],
					[
						"6483.25",
						"1.52085e-18"
					],
					[
						"6485.90",
						"1.18013e-18"
					],
					[
						"6488.55",
						"1.60489e-18"
					],
					[
						"6491.20",
						"2.14598e-18"
					],
					[
						"6493.85",
						"1.69061e-18"
					],
					[
						"6496.50",
						"1.62365e-18"
					],
					[
						"6499.15",
						"2.69496e-18"
					],
					[
						"6501.80",
						"2.74425e-18"
					],
					[
						"6504.45",
						"2.03603e-18"
					],
					[
						"6507.10",
						"2.46287e-18"
					],
					[
						"6509.75",
						"2.13596e-18"
					],
					[
						"6512.40",
						"1.74665e-18"
					],
					[
						"6515.05",
						"1.79644e-18"
					],
					[
						"6517.70",
						"1.72051e-18"
					],
					[
						"6520.35",
						"2.34544e-18"
					],
					[
						"6523.00",
						"2.00163e-18"
					],
					[
						"6525.65",
						"7.98854e-19"
					],
					[
						"6528.30",
						"9.69123e-19"
					],
					[
						"6530.95",
						"1.57306e-18"
					],
					[
						"6533.60",
						"1.52073e-18"
					],
					[
						"6536.25",
						"1.52171e-18"
					],
					[
						"6538.90",
						"1.40014e-18"
					],
					[
						"6541.55",
						"1.48255e-18"
					],
					[
						"6544.20",
						"1.68421e-18"
					],
					[
						"6546.85",
						"1.1503e-18"
					],
					[
						"6549.50",
						"9.69426e-19"
					],
					[
						"6552.15",
						"1.89274e-18"
					],
					[
						"6554.80",
						"2.01018e-18"
					],
					[
						"6557.45",
						"1.7746e-18"
					],
					[
						"6560.10",
						"2.00119e-18"
					],
					[
						"6562.75",
						"1.95147e-18"
					],
					[
						"6565.40",
						"1.93112e-18"
					],
					[
						"6568.05",
						"2.05679e-18"
					],
					[
						"6570.70",
						"2.24992e-18"
					],
					[
						"6573.35",
						"2.00191e-18"
					],
					[
						"6576.00",
						"1.63641e-18"
					],
					[
						"6578.65",
						"1.97801e-18"
					],
					[
						"6581.30",
						"2.22973e-18"
					],
					[
						"6583.95",
						"1.49705e-18"
					],
					[
						"6586.60",
						"1.06175e-18"
					],
					[
						"6589.25",
						"1.66336e-18"
					],
					[
						"6591.90",
						"1.66945e-18"
					],
					[
						"6594.55",
						"1.48047e-18"
					],
					[
						"6597.20",
						"1.63738e-18"
					],
					[
						"6599.85",
						"1.64306e-18"
					],
					[
						"6602.50",
						"1.51234e-18"
					],
					[
						"6605.15",
						"1.73598e-18"
					],
					[
						"6607.80",
						"2.10951e-18"
					],
					[
						"6610.45",
						"2.13561e-18"
					],
					[
						"6613.10",
						"1.92716e-18"
					],
					[
						"6615.75",
						"1.445e-18"
					],
					[
						"6618.40",
						"1.7398e-18"
					],
					[
						"6621.05",
						"1.56875e-18"
					],
					[
						"6623.70",
						"1.3085e-18"
					],
					[
						"6626.35",
						"1.59815e-18"
					],
					[
						"6629.00",
						"1.2128e-18"
					],
					[
						"6631.65",
						"1.60582e-18"
					],
					[
						"6634.30",
						"1.88444e-18"
					],
					[
						"6636.95",
						"1.70508e-18"
					],
					[
						"6639.60",
						"1.75537e-18"
					],
					[
						"6642.25",
						"1.85983e-18"
					],
					[
						"6644.90",
						"2.01228e-18"
					],
					[
						"6647.55",
						"1.92409e-18"
					],
					[
						"6650.20",
						"2.09823e-18"
					],
					[
						"6652.85",
						"2.07407e-18"
					],
					[
						"6655.50",
						"2.00217e-18"
					],
					[
						"6658.15",
						"1.639e-18"
					],
					[
						"6660.80",
						"1.58252e-18"
					],
					[
						"6663.45",
						"1.26625e-18"
					],
					[
						"6666.10",
						"1.5421e-18"
					],
					[
						"6668.75",
						"1.6807e-18"
					],
					[
						"6671.40",
						"1.37736e-18"
					],
					[
						"6674.05",
						"1.59891e-18"
					],
					[
						"6676.70",
						"1.91865e-18"
					],
					[
						"6679.35",
						"2.04334e-18"
					],
					[
						"6682.00",
						"2.40732e-18"
					],
					[
						"6684.65",
						"2.24882e-18"
					],
					[
						"6687.30",
						"1.83317e-18"
					],
					[
						"6689.95",
						"1.99906e-18"
					],
					[
						"6692.60",
						"1.74014e-18"
					],
					[
						"6695.25",
						"1.73539e-18"
					],
					[
						"6697.90",
						"1.52412e-18"
					],
					[
						"6700.55",
						"1.44242e-18"
					],
					[
						"6703.20",
						"1.84088e-18"
					],
					[
						"6705.85",
						"2.03598e-18"
					],
					[
						"6708.50",
						"1.78464e-18"
					],
					[
						"6711.15",
						"2.02451e-18"
					],
					[
						"6713.80",
						"2.27337e-18"
					],
					[
						"6716.45",
						"1.55655e-18"
					],
					[
						"6719.10",
						"1.88764e-18"
					],
					[
						"6721.75",
						"2.38437e-18"
					],
					[
						"6724.40",
						"1.81349e-18"
					],
					[
						"6727.05",
						"1.36698e-18"
					],
					[
						"6729.70",
						"1.51926e-18"
					],
					[
						"6732.35",
						"1.58373e-18"
					],
					[
						"6735.00",
						"1.597e-18"
					],
					[
						"6737.65",
						"1.83697e-18"
					],
					[
						"6740.30",
						"1.18546e-18"
					],
					[
						"6742.95",
						"1.60823e-18"
					],
					[
						"6745.60",
						"2.07679e-18"
					],
					[
						"6748.25",
						"7.74153e-19"
					],
					[
						"6750.90",
						"1.29842e-18"
					],
					[
						"6753.55",
						"2.23237e-18"
					],
					[
						"6756.20",
						"2.21893e-18"
					],
					[
						"6758.85",
						"1.91444e-18"
					],
					[
						"6761.50",
						"1.30974e-18"
					],
					[
						"6764.15",
						"1.41298e-18"
					],
					[
						"6766.80",
						"1.94207e-18"
					],
					[
						"6769.45",
						"1.70045e-18"
					],
					[
						"6772.10",
						"9.31943e-19"
					],
					[
						"6774.75",
						"1.39268e-18"
					],
					[
						"6777.40",
						"2.55454e-18"
					],
					[
						"6780.05",
						"2.38953e-18"
					],
					[
						"6782.70",
						"1.53938e-18"
					],
					[
						"6785.35",
						"1.46394e-18"
					],
					[
						"6788.00",
						"1.31635e-18"
					],
					[
						"6790.65",
						"1.28083e-18"
					],
					[
						"6793.30",
						"1.86339e-18"
					],
					[
						"6795.95",
						"1.79923e-18"
					],
					[
						"6798.60",
						"1.40033e-18"
					],
					[
						"6801.25",
						"1.10302e-18"
					],
					[
						"6803.90",
						"1.68131e-18"
					],
					[
						"6806.55",
						"2.22402e-18"
					],
					[
						"6809.20",
						"1.60106e-18"
					],
					[
						"6811.85",
						"1.80516e-18"
					],
					[
						"6814.50",
						"2.12843e-18"
					],
					[
						"6817.15",
						"1.84074e-18"
					],
					[
						"6819.80",
						"1.65017e-18"
					],
					[
						"6822.45",
						"1.08089e-18"
					],
					[
						"6825.10",
						"1.40411e-18"
					],
					[
						"6827.75",
						"2.51052e-18"
					],
					[
						"6830.40",
						"2.00914e-18"
					],
					[
						"6833.05",
						"1.12791e-18"
					],
					[
						"6835.70",
						"1.75787e-18"
					],
					[
						"6838.35",
						"1.7795e-18"
					],
					[
						"6841.00",
						"1.09095e-18"
					],
					[
						"6843.65",
						"1.66313e-18"
					],
					[
						"6846.30",
						"2.34269e-18"
					],
					[
						"6848.95",
						"1.71307e-18"
					],
					[
						"6851.60",
						"1.29726e-18"
					],
					[
						"6854.25",
						"2.06525e-18"
					],
					[
						"6856.90",
						"1.3954e-18"
					],
					[
						"6859.55",
						"3.13434e-19"
					],
					[
						"6862.20",
						"4.16342e-19"
					],
					[
						"6864.85",
						"1.14009e-18"
					],
					[
						"6867.50",
						"1.99095e-18"
					],
					[
						"6870.15",
						"2.13845e-18"
					],
					[
						"6872.80",
						"1.74243e-18"
					],
					[
						"6875.45",
						"1.24637e-18"
					],
					[
						"6878.10",
						"1.94807e-18"
					],
					[
						"6880.75",
						"1.99338e-18"
					],
					[
						"6883.40",
						"1.06058e-18"
					],
					[
						"6886.05",
						"1.2152e-18"
					],
					[
						"6888.70",
						"1.768e-18"
					],
					[
						"6891.35",
						"1.88179e-18"
					],
					[
						"6894.00",
						"1.50374e-18"
					],
					[
						"6896.65",
						"1.4941e-18"
					],
					[
						"6899.30",
						"1.26616e-18"
					],
					[
						"6901.95",
						"1.45336e-18"
					],
					[
						"6904.60",
						"1.83118e-18"
					],
					[
						"6907.25",
						"1.78758e-18"
					],
					[
						"6909.90",
						"2.13539e-18"
					],
					[
						"6912.55",
						"2.05278e-18"
					],
					[
						"6915.20",
						"1.50243e-18"
					],
					[
						"6917.85",
						"1.05834e-18"
					],
					[
						"6920.50",
						"1.77259e-18"
					],
					[
						"6923.15",
						"2.34492e-18"
					],
					[
						"6925.80",
						"1.98715e-18"
					],
					[
						"6928.45",
						"1.52913e-18"
					],
					[
						"6931.10",
						"1.38655e-18"
					],
					[
						"6933.75",
						"1.5508e-18"
					],
					[
						"6936.40",
						"1.4184e-18"
					],
					[
						"6939.05",
						"1.49705e-18"
					],
					[
						"6941.70",
						"2.15227e-18"
					],
					[
						"6944.35",
						"1.82066e-18"
					],
					[
						"6947.00",
						"1.46409e-18"
					],
					[
						"6949.65",
						"2.39403e-18"
					],
					[
						"6952.30",
						"1.87201e-18"
					],
					[
						"6954.95",
						"8.64583e-19"
					],
					[
						"6957.60",
						"1.17317e-18"
					],
					[
						"6960.25",
						"1.83792e-18"
					],
					[
						"6962.90",
						"2.52307e-18"
					],
					[
						"6965.55",
						"1.96758e-18"
					],
					[
						"6968.20",
						"1.23218e-18"
					],
					[
						"6970.85",
						"1.66261e-18"
					],
					[
						"6973.50",
						"1.73113e-18"
					],
					[
						"6976.15",
						"1.35122e-18"
					],
					[
						"6978.80",
						"1.24978e-18"
					],
					[
						"6981.45",
						"8.91523e-19"
					],
					[
						"6984.10",
						"8.92111e-19"
					],
					[
						"6986.75",
						"2.45269e-18"
					],
					[
						"6989.40",
						"3.02442e-18"
					],
					[
						"6992.05",
						"2.33681e-18"
					],
					[
						"6994.70",
						"1.78157e-18"
					],
					[
						"6997.35",
						"1.83834e-18"
					],
					[
						"7000.00",
						"2.36247e-18"
					],
					[
						"7002.65",
						"1.57503e-18"
					],
					[
						"7005.30",
						"1.62659e-18"
					],
					[
						"7007.95",
						"2.41207e-18"
					],
					[
						"7010.60",
						"2.06872e-18"
					],
					[
						"7013.25",
						"2.4198e-18"
					],
					[
						"7015.90",
						"2.02648e-18"
					],
					[
						"7018.55",
						"1.02225e-18"
					],
					[
						"7021.20",
						"1.70979e-18"
					],
					[
						"7023.85",
						"2.36383e-18"
					],
					[
						"7026.50",
						"1.71161e-18"
					],
					[
						"7029.15",
						"1.4595e-18"
					],
					[
						"7031.80",
						"1.72505e-18"
					],
					[
						"7034.45",
						"1.99638e-18"
					],
					[
						"7037.10",
						"1.83287e-18"
					],
					[
						"7039.75",
						"1.71525e-18"
					],
					[
						"7042.40",
						"1.64076e-18"
					],
					[
						"7045.05",
						"9.57248e-19"
					],
					[
						"7047.70",
						"1.81804e-18"
					],
					[
						"7050.35",
						"1.9865e-18"
					],
					[
						"7053.00",
						"1.03247e-18"
					],
					[
						"7055.65",
						"1.28306e-18"
					],
					[
						"7058.30",
						"1.52281e-18"
					],
					[
						"7060.95",
						"1.77488e-18"
					],
					[
						"7063.60",
						"1.72213e-18"
					],
					[
						"7066.25",
						"1.78026e-18"
					],
					[
						"7068.90",
						"1.95081e-18"
					],
					[
						"7071.55",
						"1.76379e-18"
					],
					[
						"7074.20",
						"1.81786e-18"
					],
					[
						"7076.85",
						"1.72951e-18"
					],
					[
						"7079.50",
						"1.75016e-18"
					],
					[
						"7082.15",
						"1.37092e-18"
					],
					[
						"7084.80",
						"1.56958e-18"
					],
					[
						"7087.45",
						"2.27836e-18"
					],
					[
						"7090.10",
						"2.25922e-18"
					],
					[
						"7092.75",
						"2.22242e-18"
					],
					[
						"7095.40",
						"1.8587e-18"
					],
					[
						"7098.05",
						"1.41471e-18"
					],
					[
						"7100.70",
						"1.65418e-18"
					],
					[
						"7103.35",
						"2.42122e-18"
					],
					[
						"7106.00",
						"2.59478e-18"
					],
					[
						"7108.65",
						"1.7866e-18"
					],
					[
						"7111.30",
						"1.47644e-18"
					],
					[
						"7113.95",
						"1.47306e-18"
					],
					[
						"7116.60",
						"1.20479e-18"
					],
					[
						"7119.25",
						"1.31815e-18"
					],
					[
						"7121.90",
						"1.86972e-18"
					],
					[
						"7124.55",
						"2.02992e-18"
					],
					[
						"7127.20",
						"9.8597e-19"
					],
					[
						"7129.85",
						"1.11214e-18"
					],
					[
						"7132.50",
						"1.68702e-18"
					],
					[
						"7135.15",
						"1.18756e-18"
					],
					[
						"7137.80",
						"1.58093e-18"
					],
					[
						"7140.45",
						"1.9078e-18"
					],
					[
						"7143.10",
						"2.00988e-18"
					],
					[
						"7145.75",
						"2.28423e-18"
					],
					[
						"7148.40",
						"1.69063e-18"
					],
					[
						"7151.05",
						"2.55423e-18"
					],
					[
						"7153.70",
						"3.17356e-18"
					],
					[
						"7156.35",
						"2.08872e-18"
					],
					[
						"7159.00",
						"1.77206e-18"
					],
					[
						"7161.65",
						"1.75951e-18"
					],
					[
						"7164.30",
						"1.93546e-18"
					],
					[
						"7166.95",
						"1.7858e-18"
					],
					[
						"7169.60",
						"1.3732e-18"
					],
					[
						"7172.25",
						"1.57959e-18"
					],
					[
						"7174.90",
						"2.01435e-18"
					],
					[
						"7177.55",
						"2.30279e-18"
					],
					[
						"7180.20",
						"2.67109e-18"
					],
					[
						"7182.85",
						"2.19294e-18"
					],
					[
						"7185.50",
						"1.48331e-18"
					],
					[
						"7188.15",
						"1.56605e-18"
					],
					[
						"7190.80",
						"1.57226e-18"
					],
					[
						"7193.45",
						"1.52278e-18"
					],
					[
						"7196.10",
						"1.80895e-18"
					],
					[
						"7198.75",
						"1.86965e-18"
					],
					[
						"7201.40",
						"1.4882e-18"
					],
					[
						"7204.05",
						"1.59174e-18"
					],
					[
						"7206.70",
						"1.76637e-18"
					],
					[
						"7209.35",
						"1.36682e-18"
					],
					[
						"7212.00",
						"1.21689e-18"
					],
					[
						"7214.65",
						"1.43408e-18"
					],
					[
						"7217.30",
						"1.31361e-18"
					],
					[
						"7219.95",
						"1.25267e-18"
					],
					[
						"7222.60",
						"1.74307e-18"
					],
					[
						"7225.25",
						"2.44068e-18"
					],
					[
						"7227.90",
						"2.10144e-18"
					],
					[
						"7230.55",
						"1.58703e-18"
					],
					[
						"7233.20",
						"1.25216e-18"
					],
					[
						"7235.85",
						"1.46445e-18"
					],
					[
						"7238.50",
						"2.15565e-18"
					],
					[
						"7241.15",
						"2.06236e-18"
					],
					[
						"7243.80",
						"2.00128e-18"
					],
					[
						"7246.45",
						"2.03593e-18"
					],
					[
						"7249.10",
						"1.79073e-18"
					],
					[
						"7251.75",
						"2.04692e-18"
					],
					[
						"7254.40",
						"2.35429e-18"
					],
					[
						"7257.05",
						"2.56473e-18"
					],
					[
						"7259.70",
						"2.16008e-18"
					],
					[
						"7262.35",
						"1.68765e-18"
					],
					[
						"7265.00",
						"2.42338e-18"
					],
					[
						"7267.65",
						"2.24324e-18"
					],
					[
						"7270.30",
						"1.84069e-18"
					],
					[
						"7272.95",
						"2.30622e-18"
					],
					[
						"7275.60",
						"2.51004e-18"
					],
					[
						"7278.25",
						"2.06129e-18"
					],
					[
						"7280.90",
						"2.81298e-18"
					],
					[
						"7283.55",
						"3.67803e-18"
					],
					[
						"7286.20",
						"3.13586e-18"
					],
					[
						"7288.85",
						"3.01903e-18"
					],
					[
						"7291.50",
						"2.845e-18"
					],
					[
						"7294.15",
						"2.3635e-18"
					],
					[
						"7296.80",
						"1.62676e-18"
					],
					[
						"7299.45",
						"1.78256e-18"
					],
					[
						"7302.10",
						"1.92218e-18"
					],
					[
						"7304.75",
						"1.11831e-18"
					],
					[
						"7307.40",
						"1.45186e-18"
					],
					[
						"7310.05",
						"1.6947e-18"
					],
					[
						"7312.70",
						"1.34043e-18"
					],
					[
						"7315.35",
						"1.95748e-18"
					],
					[
						"7318.00",
						"1.75132e-18"
					],
					[
						"7320.65",
						"1.38758e-18"
					],
					[
						"7323.30",
						"2.13997e-18"
					],
					[
						"7325.95",
						"2.6722e-18"
					],
					[
						"7328.60",
						"1.34306e-18"
					],
					[
						"7331.25",
						"1.25875e-18"
					],
					[
						"7333.90",
						"2.39722e-18"
					],
					[
						"7336.55",
						"-9.43908e-19"
					],
					[
						"7339.20",
						"-9.51048e-19"
					],
					[
						"7341.85",
						"2.01296e-18"
					],
					[
						"7344.50",
						"2.03221e-18"
					],
					[
						"7347.15",
						"2.09741e-18"
					],
					[
						"7349.80",
						"1.65461e-18"
					],
					[
						"7352.45",
						"2.09755e-18"
					],
					[
						"7355.10",
						"2.56217e-18"
					],
					[
						"7357.75",
						"1.54742e-18"
					],
					[
						"7360.40",
						"1.1821e-18"
					],
					[
						"7363.05",
						"2.71433e-18"
					],
					[
						"7365.70",
						"3.01269e-18"
					],
					[
						"7368.35",
						"1.42434e-18"
					],
					[
						"7371.00",
						"6.73359e-19"
					],
					[
						"7373.65",
						"1.03826e-18"
					],
					[
						"7376.30",
						"1.72196e-18"
					],
					[
						"7378.95",
						"2.30415e-18"
					],
					[
						"7381.60",
						"1.76748e-18"
					],
					[
						"7384.25",
						"1.71974e-18"
					],
					[
						"7386.90",
						"2.73855e-18"
					],
					[
						"7389.55",
						"2.15039e-18"
					],
					[
						"7392.20",
						"1.52874e-18"
					],
					[
						"7394.85",
						"2.61067e-18"
					],
					[
						"7397.50",
						"2.11201e-18"
					],
					[
						"7400.15",
						"1.3528e-18"
					],
					[
						"7402.80",
						"9.38363e-19"
					],
					[
						"7405.45",
						"8.44063e-19"
					],
					[
						"7408.10",
						"1.6695e-18"
					],
					[
						"7410.75",
						"1.94184e-18"
					],
					[
						"7413.40",
						"1.99549e-18"
					],
					[
						"7416.05",
						"1.68528e-18"
					],
					[
						"7418.70",
						"2.00899e-18"
					],
					[
						"7421.35",
						"2.6366e-18"
					],
					[
						"7424.00",
						"2.3028e-18"
					],
					[
						"7426.65",
						"1.88384e-18"
					],
					[
						"7429.30",
						"1.30341e-18"
					],
					[
						"7431.95",
						"1.76363e-18"
					],
					[
						"7434.60",
						"3.53966e-18"
					],
					[
						"7437.25",
						"2.47854e-18"
					],
					[
						"7439.90",
						"1.49605e-18"
					],
					[
						"7442.55",
						"2.27635e-18"
					],
					[
						"7445.20",
						"2.08807e-18"
					],
					[
						"7447.85",
						"2.17388e-18"
					],
					[
						"7450.50",
						"1.32754e-18"
					],
					[
						"7453.15",
						"7.22212e-19"
					],
					[
						"7455.80",
						"1.29794e-18"
					],
					[
						"7458.45",
						"1.64959e-18"
					],
					[
						"7461.10",
						"2.08619e-18"
					],
					[
						"7463.75",
						"2.27514e-18"
					],
					[
						"7466.40",
						"1.88885e-18"
					],
					[
						"7469.05",
						"7.77097e-19"
					],
					[
						"7471.70",
						"8.77291e-19"
					],
					[
						"7474.35",
						"1.66542e-18"
					],
					[
						"7477.00",
						"1.20109e-18"
					],
					[
						"7479.65",
						"1.15575e-18"
					],
					[
						"7482.30",
						"1.95683e-18"
					],
					[
						"7484.95",
						"1.61366e-18"
					],
					[
						"7487.60",
						"1.15945e-18"
					],
					[
						"7490.25",
						"1.44666e-18"
					],
					[
						"7492.90",
						"1.26273e-18"
					],
					[
						"7495.55",
						"1.07085e-18"
					],
					[
						"7498.20",
						"1.33365e-18"
					],
					[
						"7500.85",
						"2.00831e-18"
					],
					[
						"7503.50",
						"2.78159e-18"
					],
					[
						"7506.15",
						"2.85241e-18"
					],
					[
						"7508.80",
						"3.2115e-18"
					],
					[
						"7511.45",
						"2.68564e-18"
					],
					[
						"7514.10",
						"1.72526e-18"
					],
					[
						"7516.75",
						"2.0764e-18"
					],
					[
						"7519.40",
						"2.44975e-18"
					],
					[
						"7522.05",
						"2.99613e-18"
					],
					[
						"7524.70",
						"2.78336e-18"
					],
					[
						"7527.35",
						"1.92757e-18"
					],
					[
						"7530.00",
						"1.12269e-18"
					],
					[
						"7532.65",
						"1.28204e-18"
					],
					[
						"7535.30",
						"1.87785e-18"
					],
					[
						"7537.95",
						"1.56941e-18"
					],
					[
						"7540.60",
						"1.11884e-18"
					],
					[
						"7543.25",
						"1.25395e-18"
					],
					[
						"7545.90",
						"1.76734e-18"
					],
					[
						"7548.55",
						"1.26886e-18"
					],
					[
						"7551.20",
						"9.8191e-19"
					],
					[
						"7553.85",
						"1.82159e-18"
					],
					[
						"7556.50",
						"2.04943e-18"
					],
					[
						"7559.15",
						"1.85887e-18"
					],
					[
						"7561.80",
						"1.53179e-18"
					],
					[
						"7564.45",
						"1.50167e-18"
					],
					[
						"7567.10",
						"2.16974e-18"
					],
					[
						"7569.75",
						"2.38439e-18"
					],
					[
						"7572.40",
						"1.91779e-18"
					],
					[
						"7575.05",
						"2.39776e-18"
					],
					[
						"7577.70",
						"2.50246e-18"
					],
					[
						"7580.35",
						"1.69857e-18"
					],
					[
						"7583.00",
						"2.03275e-18"
					],
					[
						"7585.65",
						"3.16348e-18"
					],
					[
						"7588.30",
						"3.49031e-18"
					],
					[
						"7590.95",
						"1.02723e-18"
					],
					[
						"7593.60",
						"7.19826e-19"
					],
					[
						"7596.25",
						"2.57838e-18"
					],
					[
						"7598.90",
						"1.98251e-18"
					],
					[
						"7601.55",
						"1.62795e-18"
					],
					[
						"7604.20",
						"1.8402e-18"
					],
					[
						"7606.85",
						"2.51598e-18"
					],
					[
						"7609.50",
						"1.62109e-18"
					],
					[
						"7612.15",
						"4.26653e-19"
					],
					[
						"7614.80",
						"2.04716e-18"
					],
					[
						"7617.45",
						"1.60386e-18"
					],
					[
						"7620.10",
						"8.75755e-19"
					],
					[
						"7622.75",
						"1.22127e-18"
					],
					[
						"7625.40",
						"1.48737e-18"
					],
					[
						"7628.05",
						"2.44925e-18"
					],
					[
						"7630.70",
						"2.19992e-18"
					],
					[
						"7633.35",
						"2.17716e-18"
					],
					[
						"7636.00",
						"2.40954e-18"
					],
					[
						"7638.65",
						"2.20707e-18"
					],
					[
						"7641.30",
						"1.04504e-18"
					],
					[
						"7643.95",
						"5.63388e-19"
					],
					[
						"7646.60",
						"1.28076e-18"
					],
					[
						"7649.25",
						"1.22289e-18"
					],
					[
						"7651.90",
						"1.92392e-18"
					],
					[
						"7654.55",
						"1.60741e-18"
					],
					[
						"7657.20",
						"1.66001e-18"
					],
					[
						"7659.85",
						"1.64904e-18"
					],
					[
						"7662.50",
						"1.07027e-18"
					],
					[
						"7665.15",
						"2.34104e-19"
					],
					[
						"7667.80",
						"6.32017e-19"
					],
					[
						"7670.45",
						"2.24639e-18"
					],
					[
						"7673.10",
						"1.42362e-18"
					],
					[
						"7675.75",
						"8.38153e-19"
					],
					[
						"7678.40",
						"1.11769e-18"
					],
					[
						"7681.05",
						"2.24778e-18"
					],
					[
						"7683.70",
						"2.02276e-18"
					],
					[
						"7686.35",
						"1.54733e-18"
					],
					[
						"7689.00",
						"2.57953e-18"
					],
					[
						"7691.65",
						"2.33821e-18"
					],
					[
						"7694.30",
						"1.77251e-18"
					],
					[
						"7696.95",
						"1.9924e-18"
					],
					[
						"7699.60",
						"1.68723e-18"
					],
					[
						"7702.25",
						"4.23397e-19"
					],
					[
						"7704.90",
						"8.22552e-19"
					],
					[
						"7707.55",
						"1.73373e-18"
					],
					[
						"7710.20",
						"2.59608e-18"
					],
					[
						"7712.85",
						"3.77965e-18"
					],
					[
						"7715.50",
						"1.50763e-18"
					],
					[
						"7718.15",
						"-1.03742e-19"
					],
					[
						"7720.80",
						"3.86919e-19"
					],
					[
						"7723.45",
						"1.84344e-18"
					],
					[
						"7726.10",
						"3.00092e-18"
					],
					[
						"7728.75",
						"2.37272e-18"
					],
					[
						"7731.40",
						"1.87089e-18"
					],
					[
						"7734.05",
						"6.75647e-19"
					],
					[
						"7736.70",
						"3.95891e-19"
					],
					[
						"7739.35",
						"6.77978e-19"
					],
					[
						"7742.00",
						"7.94425e-19"
					],
					[
						"7744.65",
						"1.76359e-18"
					],
					[
						"7747.30",
						"1.72097e-18"
					],
					[
						"7749.95",
						"1.40259e-18"
					],
					[
						"7752.60",
						"2.53143e-18"
					],
					[
						"7755.25",
						"3.1768e-18"
					],
					[
						"7757.90",
						"1.72382e-18"
					],
					[
						"7760.55",
						"7.93589e-19"
					],
					[
						"7763.20",
						"2.44461e-18"
					],
					[
						"7765.85",
						"2.36611e-18"
					],
					[
						"7768.50",
						"1.32267e-18"
					],
					[
						"7771.15",
						"1.57441e-18"
					],
					[
						"7773.80",
						"1.69438e-18"
					],
					[
						"7776.45",
						"1.98257e-18"
					],
					[
						"7779.10",
						"1.80511e-18"
					],
					[
						"7781.75",
						"1.81755e-18"
					],
					[
						"7784.40",
						"1.84497e-18"
					],
					[
						"7787.05",
						"6.72146e-19"
					],
					[
						"7789.70",
						"7.53334e-19"
					],
					[
						"7792.35",
						"2.72378e-18"
					],
					[
						"7795.00",
						"3.09332e-18"
					],
					[
						"7797.65",
						"2.98446e-18"
					],
					[
						"7800.30",
						"2.96889e-18"
					],
					[
						"7802.95",
						"1.29102e-18"
					],
					[
						"7805.60",
						"1.07697e-18"
					],
					[
						"7808.25",
						"1.19766e-18"
					],
					[
						"7810.90",
						"8.20167e-19"
					],
					[
						"7813.55",
						"1.06105e-18"
					],
					[
						"7816.20",
						"1.30753e-18"
					],
					[
						"7818.85",
						"1.9908e-18"
					],
					[
						"7821.50",
						"2.46786e-18"
					],
					[
						"7824.15",
						"2.2306e-18"
					],
					[
						"7826.80",
						"1.13237e-18"
					],
					[
						"7829.45",
						"1.18944e-18"
					],
					[
						"7832.10",
						"2.30675e-18"
					],
					[
						"7834.75",
						"1.31931e-18"
					],
					[
						"7837.40",
						"4.86315e-19"
					],
					[
						"7840.05",
						"1.89596e-18"
					],
					[
						"7842.70",
						"2.57516e-18"
					],
					[
						"7845.35",
						"2.17674e-18"
					],
					[
						"7848.00",
						"1.284e-18"
					],
					[
						"7850.65",
						"1.11993e-18"
					],
					[
						"7853.30",
						"2.25714e-18"
					],
					[
						"7855.95",
						"1.36338e-18"
					],
					[
						"7858.60",
						"3.25286e-19"
					],
					[
						"7861.25",
						"1.54554e-18"
					],
					[
						"7863.90",
						"3.74868e-18"
					],
					[
						"7866.55",
						"2.43585e-18"
					],
					[
						"7869.20",
						"5.56394e-19"
					],
					[
						"7871.85",
						"1.12352e-18"
					],
					[
						"7874.50",
						"1.67513e-18"
					],
					[
						"7877.15",
						"2.41331e-18"
					],
					[
						"7879.80",
						"2.85004e-18"
					],
					[
						"7882.45",
						"3.50505e-18"
					],
					[
						"7885.10",
						"1.69197e-18"
					],
					[
						"7887.75",
						"1.0621e-18"
					],
					[
						"7890.40",
						"1.46302e-18"
					],
					[
						"7893.05",
						"3.34357e-19"
					],
					[
						"7895.70",
						"2.09323e-19"
					],
					[
						"7898.35",
						"1.6181e-18"
					],
					[
						"7901.00",
						"2.4963e-18"
					],
					[
						"7903.65",
						"1.90944e-18"
					],
					[
						"7906.30",
						"1.6676e-18"
					],
					[
						"7908.95",
						"1.01661e-18"
					],
					[
						"7911.60",
						"1.0945e-18"
					],
					[
						"7914.25",
						"2.64717e-18"
					],
					[
						"7916.90",
						"3.03588e-18"
					],
					[
						"7919.55",
						"8.70791e-19"
					],
					[
						"7922.20",
						"3.04122e-18"
					],
					[
						"7924.85",
						"5.8241e-18"
					],
					[
						"7927.50",
						"2.79707e-18"
					],
					[
						"7930.15",
						"1.77868e-18"
					],
					[
						"7932.80",
						"2.11002e-18"
					],
					[
						"7935.45",
						"1.57181e-18"
					],
					[
						"7938.10",
						"1.43007e-18"
					],
					[
						"7940.75",
						"1.72403e-18"
					],
					[
						"7943.40",
						"1.44699e-18"
					],
					[
						"7946.05",
						"9.15939e-19"
					],
					[
						"7948.70",
						"2.1649e-18"
					],
					[
						"7951.35",
						"3.04965e-18"
					],
					[
						"7954.00",
						"2.1222e-18"
					],
					[
						"7956.65",
						"1.32561e-18"
					],
					[
						"7959.30",
						"2.25331e-18"
					],
					[
						"7961.95",
						"2.53928e-18"
					],
					[
						"7964.60",
						"1.23737e-18"
					],
					[
						"7967.25",
						"-6.02678e-19"
					],
					[
						"7969.90",
						"5.49407e-20"
					],
					[
						"7972.55",
						"1.34654e-18"
					],
					[
						"7975.20",
						"1.98289e-18"
					],
					[
						"7977.85",
						"1.67616e-18"
					],
					[
						"7980.50",
						"2.07314e-18"
					],
					[
						"7983.15",
						"2.53722e-18"
					],
					[
						"7985.80",
						"-1.16352e-18"
					],
					[
						"7988.45",
						"-8.35017e-19"
					],
					[
						"7991.10",
						"1.01479e-18"
					],
					[
						"7993.75",
						"1.68221e-18"
					],
					[
						"7996.40",
						"2.14073e-18"
					],
					[
						"7999.05",
						"2.3693e-18"
					],
					[
						"8001.70",
						"2.94239e-18"
					],
					[
						"8004.35",
						"1.29626e-18"
					],
					[
						"8007.00",
						"1.04289e-18"
					],
					[
						"8009.65",
						"9.96905e-19"
					],
					[
						"8012.30",
						"1.60053e-18"
					],
					[
						"8014.95",
						"2.72733e-18"
					],
					[
						"8017.60",
						"2.29839e-18"
					],
					[
						"8020.25",
						"1.91944e-18"
					],
					[
						"8022.90",
						"2.19485e-18"
					],
					[
						"8025.55",
						"1.5829e-18"
					],
					[
						"8028.20",
						"1.16142e-18"
					],
					[
						"8030.85",
						"1.47198e-18"
					],
					[
						"8033.50",
						"3.8108e-19"
					],
					[
						"8036.15",
						"4.02785e-19"
					],
					[
						"8038.80",
						"1.77241e-18"
					],
					[
						"8041.45",
						"1.42734e-18"
					],
					[
						"8044.10",
						"1.27792e-18"
					],
					[
						"8046.75",
						"2.06773e-18"
					],
					[
						"8049.40",
						"1.60854e-18"
					],
					[
						"8052.05",
						"5.85692e-19"
					],
					[
						"8054.70",
						"7.88746e-20"
					],
					[
						"8057.35",
						"9.52893e-19"
					],
					[
						"8060.00",
						"2.1906e-18"
					],
					[
						"8062.65",
						"1.57316e-18"
					],
					[
						"8065.30",
						"1.39425e-18"
					],
					[
						"8067.95",
						"2.64497e-18"
					],
					[
						"8070.60",
						"1.58422e-18"
					],
					[
						"8073.25",
						"2.69916e-19"
					],
					[
						"8075.90",
						"3.62458e-19"
					],
					[
						"8078.55",
						"8.42198e-19"
					],
					[
						"8081.20",
						"6.41383e-19"
					],
					[
						"8083.85",
						"1.01563e-18"
					],
					[
						"8086.50",
						"2.63718e-18"
					],
					[
						"8089.15",
						"3.0916e-18"
					],
					[
						"8091.80",
						"3.12918e-18"
					],
					[
						"8094.45",
						"2.09202e-18"
					],
					[
						"8097.10",
						"9.40675e-19"
					],
					[
						"8099.75",
						"1.65224e-18"
					],
					[
						"8102.40",
						"2.32402e-18"
					],
					[
						"8105.05",
						"8.93107e-19"
					],
					[
						"8107.70",
						"1.47434e-18"
					],
					[
						"8110.35",
						"3.34845e-18"
					],
					[
						"8113.00",
						"2.71618e-18"
					],
					[
						"8115.65",
						"2.1049e-18"
					],
					[
						"8118.30",
						"1.91084e-18"
					],
					[
						"8120.95",
						"1.23488e-18"
					],
					[
						"8123.60",
						"2.41517e-18"
					],
					[
						"8126.25",
						"2.8916e-18"
					],
					[
						"8128.90",
						"2.31039e-18"
					],
					[
						"8131.55",
						"1.91104e-18"
					],
					[
						"8134.20",
						"1.76267e-18"
					],
					[
						"8136.85",
						"1.98559e-18"
					],
					[
						"8139.50",
						"1.70688e-18"
					],
					[
						"8142.15",
						"7.29472e-19"
					],
					[
						"8144.80",
						"1.24105e-18"
					],
					[
						"8147.45",
						"2.29985e-18"
					],
					[
						"8150.10",
						"1.04534e-18"
					],
					[
						"8152.75",
						"5.04754e-19"
					],
					[
						"8155.40",
						"1.81769e-18"
					],
					[
						"8158.05",
						"1.98906e-18"
					],
					[
						"8160.70",
						"1.10042e-18"
					],
					[
						"8163.35",
						"1.41444e-18"
					],
					[
						"8166.00",
						"2.31397e-18"
					],
					[
						"8168.65",
						"2.14456e-18"
					],
					[
						"8171.30",
						"1.09155e-18"
					],
					[
						"8173.95",
						"4.92397e-19"
					],
					[
						"8176.60",
						"5.32894e-19"
					],
					[
						"8179.25",
						"9.24372e-19"
					],
					[
						"8181.90",
						"1.0213e-18"
					],
					[
						"8184.55",
						"1.25746e-18"
					],
					[
						"8187.20",
						"2.19039e-18"
					],
					[
						"8189.85",
						"1.05996e-18"
					],
					[
						"8192.50",
						"1.32351e-18"
					],
					[
						"8195.15",
						"2.62691e-18"
					],
					[
						"8197.80",
						"2.82789e-18"
					],
					[
						"8200.45",
						"1.95844e-18"
					],
					[
						"8203.10",
						"4.19246e-19"
					],
					[
						"8205.75",
						"7.94802e-19"
					],
					[
						"8208.40",
						"1.64946e-18"
					],
					[
						"8211.05",
						"8.82195e-19"
					],
					[
						"8213.70",
						"1.76921e-18"
					],
					[
						"8216.35",
						"2.69664e-18"
					],
					[
						"8219.00",
						"7.60392e-19"
					],
					[
						"8221.65",
						"1.63409e-18"
					],
					[
						"8224.30",
						"2.65628e-18"
					],
					[
						"8226.95",
						"9.59394e-19"
					],
					[
						"8229.60",
						"2.7805e-19"
					],
					[
						"8232.25",
						"8.79579e-19"
					],
					[
						"8234.90",
						"9.7111e-19"
					],
					[
						"8237.55",
						"2.51164e-19"
					],
					[
						"8240.20",
						"1.09775e-18"
					],
					[
						"8242.85",
						"2.17151e-18"
					],
					[
						"8245.50",
						"1.81589e-18"
					],
					[
						"8248.15",
						"2.2291e-18"
					],
					[
						"8250.80",
						"1.7913e-18"
					],
					[
						"8253.45",
						"1.27927e-18"
					],
					[
						"8256.10",
						"2.63686e-18"
					],
					[
						"8258.75",
						"2.35631e-18"
					],
					[
						"8261.40",
						"9.49705e-19"
					],
					[
						"8264.05",
						"3.64525e-19"
					],
					[
						"8266.70",
						"7.96485e-20"
					],
					[
						"8269.35",
						"1.61828e-18"
					],
					[
						"8272.00",
						"2.29675e-18"
					],
					[
						"8274.65",
						"8.014e-19"
					],
					[
						"8277.30",
						"6.33182e-19"
					],
					[
						"8279.95",
						"5.76383e-21"
					],
					[
						"8282.60",
						"-7.18562e-19"
					],
					[
						"8285.25",
						"1.68339e-18"
					],
					[
						"8287.90",
						"3.25015e-18"
					],
					[
						"8290.55",
						"3.37634e-18"
					],
					[
						"8293.20",
						"1.29935e-18"
					],
					[
						"8295.85",
						"2.31616e-18"
					],
					[
						"8298.50",
						"1.51178e-18"
					],
					[
						"8301.15",
						"3.1095e-19"
					],
					[
						"8303.80",
						"3.20108e-18"
					],
					[
						"8306.45",
						"2.98054e-18"
					],
					[
						"8309.10",
						"3.02848e-18"
					],
					[
						"8311.75",
						"1.6578e-18"
					],
					[
						"8314.40",
						"1.07886e-18"
					],
					[
						"8317.05",
						"1.85969e-18"
					],
					[
						"8319.70",
						"1.04835e-18"
					],
					[
						"8322.35",
						"8.47311e-19"
					],
					[
						"8325.00",
						"2.77932e-18"
					],
					[
						"8327.65",
						"2.15379e-18"
					],
					[
						"8330.30",
						"9.99477e-19"
					],
					[
						"8332.95",
						"2.96505e-18"
					],
					[
						"8335.60",
						"2.39655e-18"
					],
					[
						"8338.25",
						"2.3395e-18"
					],
					[
						"8340.90",
						"4.77667e-18"
					],
					[
						"8343.55",
						"2.05935e-18"
					],
					[
						"8346.20",
						"4.75617e-19"
					],
					[
						"8348.85",
						"2.43098e-18"
					],
					[
						"8351.50",
						"1.85634e-18"
					],
					[
						"8354.15",
						"2.01502e-18"
					],
					[
						"8356.80",
						"2.97281e-18"
					],
					[
						"8359.45",
						"1.35261e-18"
					],
					[
						"8362.10",
						"1.20294e-18"
					],
					[
						"8364.75",
						"3.34267e-18"
					],
					[
						"8367.40",
						"1.78452e-18"
					],
					[
						"8370.05",
						"-1.451e-19"
					],
					[
						"8372.70",
						"1.42526e-18"
					],
					[
						"8375.35",
						"2.19959e-18"
					],
					[
						"8378.00",
						"2.18589e-18"
					],
					[
						"8380.65",
						"1.95258e-18"
					],
					[
						"8383.30",
						"3.82656e-19"
					],
					[
						"8385.95",
						"8.32204e-20"
					],
					[
						"8388.60",
						"2.2783e-18"
					],
					[
						"8391.25",
						"1.77773e-18"
					],
					[
						"8393.90",
						"-4.98726e-19"
					],
					[
						"8396.55",
						"-4.23563e-19"
					],
					[
						"8399.20",
						"8.50495e-19"
					],
					[
						"8401.85",
						"2.40894e-18"
					],
					[
						"8404.50",
						"3.17594e-18"
					],
					[
						"8407.15",
						"7.68516e-19"
					],
					[
						"8409.80",
						"3.89894e-19"
					],
					[
						"8412.45",
						"1.70895e-18"
					],
					[
						"8415.10",
						"4.05049e-19"
					],
					[
						"8417.75",
						"-5.2039e-19"
					],
					[
						"8420.40",
						"5.25608e-20"
					],
					[
						"8423.05",
						"2.18374e-19"
					],
					[
						"8425.70",
						"-2.54144e-19"
					],
					[
						"8428.35",
						"3.73831e-19"
					],
					[
						"8431.00",
						"1.72955e-18"
					],
					[
						"8433.65",
						"1.52642e-18"
					],
					[
						"8436.30",
						"8.91148e-19"
					],
					[
						"8438.95",
						"1.52578e-18"
					],
					[
						"8441.60",
						"2.81598e-19"
					],
					[
						"8444.25",
						"1.30823e-18"
					],
					[
						"8446.90",
						"7.53286e-19"
					],
					[
						"8449.55",
						"2.96336e-19"
					],
					[
						"8452.20",
						"3.49862e-20"
					],
					[
						"8454.85",
						"-2.9642e-19"
					],
					[
						"8457.50",
						"-5.38863e-20"
					],
					[
						"8460.15",
						"2.42004e-18"
					],
					[
						"8462.80",
						"1.48763e-18"
					],
					[
						"8465.45",
						"-1.0724e-18"
					],
					[
						"8468.10",
						"2.03951e-19"
					],
					[
						"8470.75",
						"1.24038e-18"
					],
					[
						"8473.40",
						"1.43989e-18"
					],
					[
						"8476.05",
						"1.3625e-18"
					],
					[
						"8478.70",
						"1.97867e-18"
					],
					[
						"8481.35",
						"2.67989e-18"
					],
					[
						"8484.00",
						"1.25109e-18"
					],
					[
						"8486.65",
						"3.84875e-19"
					],
					[
						"8489.30",
						"1.48931e-18"
					],
					[
						"8491.95",
						"1.85091e-18"
					],
					[
						"8494.60",
						"2.58301e-18"
					],
					[
						"8497.25",
						"2.9482e-18"
					],
					[
						"8499.90",
						"1.83494e-18"
					],
					[
						"8502.55",
						"9.79888e-19"
					],
					[
						"8505.20",
						"1.15337e-18"
					],
					[
						"8507.85",
						"4.31129e-20"
					],
					[
						"8510.50",
						"-5.28333e-19"
					],
					[
						"8513.15",
						"6.7866e-19"
					],
					[
						"8515.80",
						"1.33298e-18"
					],
					[
						"8518.45",
						"2.30594e-18"
					],
					[
						"8521.10",
						"2.09796e-18"
					],
					[
						"8523.75",
						"1.54079e-18"
					],
					[
						"8526.40",
						"2.04934e-18"
					],
					[
						"8529.05",
						"8.20749e-19"
					],
					[
						"8531.70",
						"2.69906e-19"
					],
					[
						"8534.35",
						"2.19105e-18"
					],
					[
						"8537.00",
						"2.78066e-18"
					],
					[
						"8539.65",
						"1.56441e-18"
					],
					[
						"8542.30",
						"8.6274e-19"
					],
					[
						"8544.95",
						"5.61883e-19"
					],
					[
						"8547.60",
						"2.17602e-18"
					],
					[
						"8550.25",
						"1.70365e-18"
					],
					[
						"8552.90",
						"8.70248e-19"
					],
					[
						"8555.55",
						"6.3426e-19"
					],
					[
						"8558.20",
						"1.54039e-18"
					],
					[
						"8560.85",
						"1.45836e-18"
					],
					[
						"8563.50",
						"7.07933e-19"
					],
					[
						"8566.15",
						"2.41336e-19"
					],
					[
						"8568.80",
						"-2.81339e-19"
					],
					[
						"8571.45",
						"1.31433e-18"
					],
					[
						"8574.10",
						"1.17741e-18"
					],
					[
						"8576.75",
						"1.45081e-18"
					],
					[
						"8579.40",
						"1.50412e-18"
					],
					[
						"8582.05",
						"1.22336e-18"
					],
					[
						"8584.70",
						"5.70204e-19"
					],
					[
						"8587.35",
						"-9.57276e-19"
					],
					[
						"8590.00",
						"6.51056e-19"
					],
					[
						"8592.65",
						"2.58417e-18"
					],
					[
						"8595.30",
						"2.23209e-18"
					],
					[
						"8597.95",
						"1.0883e-18"
					],
					[
						"8600.60",
						"1.99683e-18"
					],
					[
						"8603.25",
						"1.58925e-18"
					],
					[
						"8605.90",
						"1.66431e-19"
					],
					[
						"8608.55",
						"8.8565e-19"
					],
					[
						"8611.20",
						"5.6362e-19"
					],
					[
						"8613.85",
						"2.65417e-19"
					],
					[
						"8616.50",
						"1.68406e-18"
					],
					[
						"8619.15",
						"1.89478e-18"
					],
					[
						"8621.80",
						"2.03541e-18"
					],
					[
						"8624.45",
						"2.71542e-18"
					],
					[
						"8627.10",
						"6.88908e-19"
					],
					[
						"8629.75",
						"7.10717e-19"
					],
					[
						"8632.40",
						"2.33095e-18"
					],
					[
						"8635.05",
						"2.0684e-18"
					],
					[
						"8637.70",
						"1.96836e-18"
					],
					[
						"8640.35",
						"1.87064e-18"
					],
					[
						"8643.00",
						"1.90178e-18"
					],
					[
						"8645.65",
						"3.72106e-19"
					],
					[
						"8648.30",
						"3.13687e-20"
					],
					[
						"8650.95",
						"1.76624e-18"
					],
					[
						"8653.60",
						"2.68647e-18"
					],
					[
						"8656.25",
						"-9.51193e-19"
					],
					[
						"8658.90",
						"-3.37807e-19"
					],
					[
						"8661.55",
						"2.44982e-18"
					],
					[
						"8664.20",
						"1.29438e-18"
					],
					[
						"8666.85",
						"2.30094e-18"
					],
					[
						"8669.50",
						"2.33582e-18"
					],
					[
						"8672.15",
						"8.6733e-19"
					],
					[
						"8674.80",
						"7.58136e-19"
					],
					[
						"8677.45",
						"3.85665e-19"
					],
					[
						"8680.10",
						"1.41466e-18"
					],
					[
						"8682.75",
						"1.80892e-18"
					],
					[
						"8685.40",
						"2.34381e-18"
					],
					[
						"8688.05",
						"2.11025e-18"
					],
					[
						"8690.70",
						"1.59355e-18"
					],
					[
						"8693.35",
						"2.08861e-18"
					],
					[
						"8696.00",
						"1.62072e-18"
					],
					[
						"8698.65",
						"1.0255e-18"
					],
					[
						"8701.30",
						"1.36018e-18"
					],
					[
						"8703.95",
						"9.73925e-19"
					],
					[
						"8706.60",
						"1.70153e-18"
					],
					[
						"8709.25",
						"2.96389e-18"
					],
					[
						"8711.90",
						"8.95584e-19"
					],
					[
						"8714.55",
						"-4.72563e-19"
					],
					[
						"8717.20",
						"5.19022e-19"
					],
					[
						"8719.85",
						"5.42307e-19"
					],
					[
						"8722.50",
						"5.50258e-19"
					],
					[
						"8725.15",
						"1.27376e-18"
					],
					[
						"8727.80",
						"2.89111e-18"
					],
					[
						"8730.45",
						"2.88637e-18"
					],
					[
						"8733.10",
						"1.32014e-18"
					],
					[
						"8735.75",
						"1.5952e-18"
					],
					[
						"8738.40",
						"1.50626e-18"
					],
					[
						"8741.05",
						"8.55392e-19"
					],
					[
						"8743.70",
						"6.18205e-19"
					],
					[
						"8746.35",
						"7.90915e-19"
					],
					[
						"8749.00",
						"1.59619e-18"
					],
					[
						"8751.65",
						"2.36125e-18"
					],
					[
						"8754.30",
						"2.79545e-18"
					],
					[
						"8756.95",
						"2.23161e-18"
					],
					[
						"8759.60",
						"4.35054e-18"
					],
					[
						"8762.25",
						"5.00635e-18"
					],
					[
						"8764.90",
						"2.22983e-18"
					],
					[
						"8767.55",
						"2.89977e-19"
					],
					[
						"8770.20",
						"7.29315e-20"
					],
					[
						"8772.85",
						"9.78204e-19"
					],
					[
						"8775.50",
						"1.65359e-18"
					],
					[
						"8778.15",
						"2.21878e-18"
					],
					[
						"8780.80",
						"1.29588e-18"
					],
					[
						"8783.45",
						"1.25003e-19"
					],
					[
						"8786.10",
						"1.33285e-18"
					],
					[
						"8788.75",
						"2.14252e-18"
					],
					[
						"8791.40",
						"7.80103e-19"
					],
					[
						"8794.05",
						"8.28661e-19"
					],
					[
						"8796.70",
						"7.07799e-19"
					],
					[
						"8799.35",
						"7.74372e-19"
					],
					[
						"8802.00",
						"1.99052e-18"
					],
					[
						"8804.65",
						"2.08303e-18"
					],
					[
						"8807.30",
						"1.11399e-18"
					],
					[
						"8809.95",
						"2.47994e-18"
					],
					[
						"8812.60",
						"2.05146e-18"
					],
					[
						"8815.25",
						"-5.23229e-21"
					],
					[
						"8817.90",
						"1.10801e-18"
					],
					[
						"8820.55",
						"-2.14549e-18"
					],
					[
						"8823.20",
						"-3.17546e-18"
					],
					[
						"8825.85",
						"1.19816e-18"
					],
					[
						"8828.50",
						"1.17455e-18"
					],
					[
						"8831.15",
						"1.36076e-18"
					],
					[
						"8833.80",
						"3.09431e-18"
					],
					[
						"8836.45",
						"7.28278e-19"
					],
					[
						"8839.10",
						"-1.02359e-18"
					],
					[
						"8841.75",
						"8.34752e-19"
					],
					[
						"8844.40",
						"4.45035e-18"
					],
					[
						"8847.05",
						"3.43853e-18"
					],
					[
						"8849.70",
						"8.00808e-19"
					],
					[
						"8852.35",
						"1.88202e-18"
					],
					[
						"8855.00",
						"3.18976e-18"
					],
					[
						"8857.65",
						"2.39167e-18"
					],
					[
						"8860.30",
						"-4.40221e-19"
					],
					[
						"8862.95",
						"1.84272e-19"
					],
					[
						"8865.60",
						"1.65328e-18"
					],
					[
						"8868.25",
						"2.10363e-18"
					],
					[
						"8870.90",
						"-4.42202e-20"
					],
					[
						"8873.55",
						"-1.63904e-18"
					],
					[
						"8876.20",
						"1.35227e-18"
					],
					[
						"8878.85",
						"3.49575e-18"
					],
					[
						"8881.50",
						"3.57078e-18"
					],
					[
						"8884.15",
						"3.40531e-18"
					],
					[
						"8886.80",
						"3.72235e-18"
					],
					[
						"8889.45",
						"2.54841e-18"
					],
					[
						"8892.10",
						"-1.0027e-18"
					],
					[
						"8894.75",
						"-1.97458e-18"
					],
					[
						"8897.40",
						"1.15196e-18"
					],
					[
						"8900.05",
						"2.77802e-18"
					],
					[
						"8902.70",
						"1.87031e-18"
					],
					[
						"8905.35",
						"1.4971e-18"
					],
					[
						"8908.00",
						"3.29894e-18"
					],
					[
						"8910.65",
						"2.00145e-18"
					],
					[
						"8913.30",
						"2.95468e-18"
					],
					[
						"8915.95",
						"5.14643e-18"
					],
					[
						"8918.60",
						"2.12492e-18"
					],
					[
						"8921.25",
						"1.18305e-18"
					],
					[
						"8923.90",
						"2.04415e-18"
					],
					[
						"8926.55",
						"3.52033e-18"
					],
					[
						"8929.20",
						"2.27562e-18"
					],
					[
						"8931.85",
						"1.68467e-18"
					],
					[
						"8934.50",
						"3.31279e-18"
					]
				],
				"source":"1"
			}
		]
	}
}